{"brand": "NXP", "family": "K5", "name": "MK52D10", "bits": 32, "mode": 1, "segments": [{"name": "SRAM", "start": "0x1fff0000", "end": "0x2000ffff", "size": "0x20000", "type": "DATA"}], "peripherals": [{"name": "FTFL_FlashConfig", "start": "0x400", "end": "0x40f", "size": "0x10", "comment": "", "registers": [{"name": "BACKKEY3", "offset": "0x0", "size": "0x8"}, {"name": "BACKKEY2", "offset": "0x1", "size": "0x8"}, {"name": "BACKKEY1", "offset": "0x2", "size": "0x8"}, {"name": "BACKKEY0", "offset": "0x3", "size": "0x8"}, {"name": "BACKKEY7", "offset": "0x4", "size": "0x8"}, {"name": "BACKKEY6", "offset": "0x5", "size": "0x8"}, {"name": "BACKKEY5", "offset": "0x6", "size": "0x8"}, {"name": "BACKKEY4", "offset": "0x7", "size": "0x8"}, {"name": "FPROT3", "offset": "0x8", "size": "0x8"}, {"name": "FPROT2", "offset": "0x9", "size": "0x8"}, {"name": "FPROT1", "offset": "0xa", "size": "0x8"}, {"name": "FPROT0", "offset": "0xb", "size": "0x8"}, {"name": "FSEC", "offset": "0xc", "size": "0x8"}, {"name": "FOPT", "offset": "0xd", "size": "0x8"}, {"name": "FEPROT", "offset": "0xe", "size": "0x8"}, {"name": "FDPROT", "offset": "0xf", "size": "0x8"}]}, {"name": "AIPS0", "start": "0x40000000", "end": "0x4000006f", "size": "0x70", "comment": "", "registers": [{"name": "MPRA", "offset": "0x0"}, {"name": "PACRA", "offset": "0x20"}, {"name": "PACRB", "offset": "0x24"}, {"name": "PACRC", "offset": "0x28"}, {"name": "PACRD", "offset": "0x2c"}, {"name": "PACRE", "offset": "0x40"}, {"name": "PACRF", "offset": "0x44"}, {"name": "PACRG", "offset": "0x48"}, {"name": "PACRH", "offset": "0x4c"}, {"name": "PACRI", "offset": "0x50"}, {"name": "PACRJ", "offset": "0x54"}, {"name": "PACRK", "offset": "0x58"}, {"name": "PACRL", "offset": "0x5c"}, {"name": "PACRM", "offset": "0x60"}, {"name": "PACRN", "offset": "0x64"}, {"name": "PACRO", "offset": "0x68"}, {"name": "PACRP", "offset": "0x6c"}]}, {"name": "AIPS1", "start": "0x40080000", "end": "0x4008006f", "size": "0x70", "comment": "", "registers": [{"name": "MPRA", "offset": "0x0"}, {"name": "PACRA", "offset": "0x20"}, {"name": "PACRB", "offset": "0x24"}, {"name": "PACRC", "offset": "0x28"}, {"name": "PACRD", "offset": "0x2c"}, {"name": "PACRE", "offset": "0x40"}, {"name": "PACRF", "offset": "0x44"}, {"name": "PACRG", "offset": "0x48"}, {"name": "PACRH", "offset": "0x4c"}, {"name": "PACRI", "offset": "0x50"}, {"name": "PACRJ", "offset": "0x54"}, {"name": "PACRK", "offset": "0x58"}, {"name": "PACRL", "offset": "0x5c"}, {"name": "PACRM", "offset": "0x60"}, {"name": "PACRN", "offset": "0x64"}, {"name": "PACRO", "offset": "0x68"}, {"name": "PACRP", "offset": "0x6c"}]}, {"name": "AXBS", "start": "0x40004000", "end": "0x40004d03", "size": "0xd04", "comment": "", "registers": [{"name": "PRS0", "offset": "0x0"}, {"name": "PRS1", "offset": "0x100"}, {"name": "PRS2", "offset": "0x200"}, {"name": "PRS3", "offset": "0x300"}, {"name": "PRS4", "offset": "0x400"}, {"name": "CRS0", "offset": "0x10"}, {"name": "CRS1", "offset": "0x110"}, {"name": "CRS2", "offset": "0x210"}, {"name": "CRS3", "offset": "0x310"}, {"name": "CRS4", "offset": "0x410"}, {"name": "MGPCR0", "offset": "0x800"}, {"name": "MGPCR1", "offset": "0x900"}, {"name": "MGPCR2", "offset": "0xa00"}, {"name": "MGPCR3", "offset": "0xb00"}, {"name": "MGPCR4", "offset": "0xc00"}, {"name": "MGPCR5", "offset": "0xd00"}]}, {"name": "DMA", "start": "0x40008000", "end": "0x400091ff", "size": "0x1200", "comment": "", "registers": [{"name": "CR", "offset": "0x0"}, {"name": "ES", "offset": "0x4"}, {"name": "ERQ", "offset": "0xc"}, {"name": "EEI", "offset": "0x14"}, {"name": "CEEI", "offset": "0x18", "size": "0x8"}, {"name": "SEEI", "offset": "0x19", "size": "0x8"}, {"name": "CERQ", "offset": "0x1a", "size": "0x8"}, {"name": "SERQ", "offset": "0x1b", "size": "0x8"}, {"name": "CDNE", "offset": "0x1c", "size": "0x8"}, {"name": "SSRT", "offset": "0x1d", "size": "0x8"}, {"name": "CERR", "offset": "0x1e", "size": "0x8"}, {"name": "CINT", "offset": "0x1f", "size": "0x8"}, {"name": "INT", "offset": "0x24"}, {"name": "ERR", "offset": "0x2c"}, {"name": "HRS", "offset": "0x34"}, {"name": "DCHPRI3", "offset": "0x100", "size": "0x8"}, {"name": "DCHPRI2", "offset": "0x101", "size": "0x8"}, {"name": "DCHPRI1", "offset": "0x102", "size": "0x8"}, {"name": "DCHPRI0", "offset": "0x103", "size": "0x8"}, {"name": "DCHPRI7", "offset": "0x104", "size": "0x8"}, {"name": "DCHPRI6", "offset": "0x105", "size": "0x8"}, {"name": "DCHPRI5", "offset": "0x106", "size": "0x8"}, {"name": "DCHPRI4", "offset": "0x107", "size": "0x8"}, {"name": "DCHPRI11", "offset": "0x108", "size": "0x8"}, {"name": "DCHPRI10", "offset": "0x109", "size": "0x8"}, {"name": "DCHPRI9", "offset": "0x10a", "size": "0x8"}, {"name": "DCHPRI8", "offset": "0x10b", "size": "0x8"}, {"name": "DCHPRI15", "offset": "0x10c", "size": "0x8"}, {"name": "DCHPRI14", "offset": "0x10d", "size": "0x8"}, {"name": "DCHPRI13", "offset": "0x10e", "size": "0x8"}, {"name": "DCHPRI12", "offset": "0x10f", "size": "0x8"}, {"name": "TCD0_SADDR", "offset": "0x1000"}, {"name": "TCD1_SADDR", "offset": "0x1020"}, {"name": "TCD2_SADDR", "offset": "0x1040"}, {"name": "TCD3_SADDR", "offset": "0x1060"}, {"name": "TCD4_SADDR", "offset": "0x1080"}, {"name": "TCD5_SADDR", "offset": "0x10a0"}, {"name": "TCD6_SADDR", "offset": "0x10c0"}, {"name": "TCD7_SADDR", "offset": "0x10e0"}, {"name": "TCD8_SADDR", "offset": "0x1100"}, {"name": "TCD9_SADDR", "offset": "0x1120"}, {"name": "TCD10_SADDR", "offset": "0x1140"}, {"name": "TCD11_SADDR", "offset": "0x1160"}, {"name": "TCD12_SADDR", "offset": "0x1180"}, {"name": "TCD13_SADDR", "offset": "0x11a0"}, {"name": "TCD14_SADDR", "offset": "0x11c0"}, {"name": "TCD15_SADDR", "offset": "0x11e0"}, {"name": "TCD0_SOFF", "offset": "0x1004", "size": "0x10"}, {"name": "TCD1_SOFF", "offset": "0x1024", "size": "0x10"}, {"name": "TCD2_SOFF", "offset": "0x1044", "size": "0x10"}, {"name": "TCD3_SOFF", "offset": "0x1064", "size": "0x10"}, {"name": "TCD4_SOFF", "offset": "0x1084", "size": "0x10"}, {"name": "TCD5_SOFF", "offset": "0x10a4", "size": "0x10"}, {"name": "TCD6_SOFF", "offset": "0x10c4", "size": "0x10"}, {"name": "TCD7_SOFF", "offset": "0x10e4", "size": "0x10"}, {"name": "TCD8_SOFF", "offset": "0x1104", "size": "0x10"}, {"name": "TCD9_SOFF", "offset": "0x1124", "size": "0x10"}, {"name": "TCD10_SOFF", "offset": "0x1144", "size": "0x10"}, {"name": "TCD11_SOFF", "offset": "0x1164", "size": "0x10"}, {"name": "TCD12_SOFF", "offset": "0x1184", "size": "0x10"}, {"name": "TCD13_SOFF", "offset": "0x11a4", "size": "0x10"}, {"name": "TCD14_SOFF", "offset": "0x11c4", "size": "0x10"}, {"name": "TCD15_SOFF", "offset": "0x11e4", "size": "0x10"}, {"name": "TCD0_ATTR", "offset": "0x1006", "size": "0x10"}, {"name": "TCD1_ATTR", "offset": "0x1026", "size": "0x10"}, {"name": "TCD2_ATTR", "offset": "0x1046", "size": "0x10"}, {"name": "TCD3_ATTR", "offset": "0x1066", "size": "0x10"}, {"name": "TCD4_ATTR", "offset": "0x1086", "size": "0x10"}, {"name": "TCD5_ATTR", "offset": "0x10a6", "size": "0x10"}, {"name": "TCD6_ATTR", "offset": "0x10c6", "size": "0x10"}, {"name": "TCD7_ATTR", "offset": "0x10e6", "size": "0x10"}, {"name": "TCD8_ATTR", "offset": "0x1106", "size": "0x10"}, {"name": "TCD9_ATTR", "offset": "0x1126", "size": "0x10"}, {"name": "TCD10_ATTR", "offset": "0x1146", "size": "0x10"}, {"name": "TCD11_ATTR", "offset": "0x1166", "size": "0x10"}, {"name": "TCD12_ATTR", "offset": "0x1186", "size": "0x10"}, {"name": "TCD13_ATTR", "offset": "0x11a6", "size": "0x10"}, {"name": "TCD14_ATTR", "offset": "0x11c6", "size": "0x10"}, {"name": "TCD15_ATTR", "offset": "0x11e6", "size": "0x10"}, {"name": "TCD0_NBYTES_MLNO", "offset": "0x1008"}, {"name": "TCD1_NBYTES_MLNO", "offset": "0x1028"}, {"name": "TCD2_NBYTES_MLNO", "offset": "0x1048"}, {"name": "TCD3_NBYTES_MLNO", "offset": "0x1068"}, {"name": "TCD4_NBYTES_MLNO", "offset": "0x1088"}, {"name": "TCD5_NBYTES_MLNO", "offset": "0x10a8"}, {"name": "TCD6_NBYTES_MLNO", "offset": "0x10c8"}, {"name": "TCD7_NBYTES_MLNO", "offset": "0x10e8"}, {"name": "TCD8_NBYTES_MLNO", "offset": "0x1108"}, {"name": "TCD9_NBYTES_MLNO", "offset": "0x1128"}, {"name": "TCD10_NBYTES_MLNO", "offset": "0x1148"}, {"name": "TCD11_NBYTES_MLNO", "offset": "0x1168"}, {"name": "TCD12_NBYTES_MLNO", "offset": "0x1188"}, {"name": "TCD13_NBYTES_MLNO", "offset": "0x11a8"}, {"name": "TCD14_NBYTES_MLNO", "offset": "0x11c8"}, {"name": "TCD15_NBYTES_MLNO", "offset": "0x11e8"}, {"name": "TCD0_NBYTES_MLOFFNO", "offset": "0x1008"}, {"name": "TCD1_NBYTES_MLOFFNO", "offset": "0x1028"}, {"name": "TCD2_NBYTES_MLOFFNO", "offset": "0x1048"}, {"name": "TCD3_NBYTES_MLOFFNO", "offset": "0x1068"}, {"name": "TCD4_NBYTES_MLOFFNO", "offset": "0x1088"}, {"name": "TCD5_NBYTES_MLOFFNO", "offset": "0x10a8"}, {"name": "TCD6_NBYTES_MLOFFNO", "offset": "0x10c8"}, {"name": "TCD7_NBYTES_MLOFFNO", "offset": "0x10e8"}, {"name": "TCD8_NBYTES_MLOFFNO", "offset": "0x1108"}, {"name": "TCD9_NBYTES_MLOFFNO", "offset": "0x1128"}, {"name": "TCD10_NBYTES_MLOFFNO", "offset": "0x1148"}, {"name": "TCD11_NBYTES_MLOFFNO", "offset": "0x1168"}, {"name": "TCD12_NBYTES_MLOFFNO", "offset": "0x1188"}, {"name": "TCD13_NBYTES_MLOFFNO", "offset": "0x11a8"}, {"name": "TCD14_NBYTES_MLOFFNO", "offset": "0x11c8"}, {"name": "TCD15_NBYTES_MLOFFNO", "offset": "0x11e8"}, {"name": "TCD0_NBYTES_MLOFFYES", "offset": "0x1008"}, {"name": "TCD1_NBYTES_MLOFFYES", "offset": "0x1028"}, {"name": "TCD2_NBYTES_MLOFFYES", "offset": "0x1048"}, {"name": "TCD3_NBYTES_MLOFFYES", "offset": "0x1068"}, {"name": "TCD4_NBYTES_MLOFFYES", "offset": "0x1088"}, {"name": "TCD5_NBYTES_MLOFFYES", "offset": "0x10a8"}, {"name": "TCD6_NBYTES_MLOFFYES", "offset": "0x10c8"}, {"name": "TCD7_NBYTES_MLOFFYES", "offset": "0x10e8"}, {"name": "TCD8_NBYTES_MLOFFYES", "offset": "0x1108"}, {"name": "TCD9_NBYTES_MLOFFYES", "offset": "0x1128"}, {"name": "TCD10_NBYTES_MLOFFYES", "offset": "0x1148"}, {"name": "TCD11_NBYTES_MLOFFYES", "offset": "0x1168"}, {"name": "TCD12_NBYTES_MLOFFYES", "offset": "0x1188"}, {"name": "TCD13_NBYTES_MLOFFYES", "offset": "0x11a8"}, {"name": "TCD14_NBYTES_MLOFFYES", "offset": "0x11c8"}, {"name": "TCD15_NBYTES_MLOFFYES", "offset": "0x11e8"}, {"name": "TCD0_SLAST", "offset": "0x100c"}, {"name": "TCD1_SLAST", "offset": "0x102c"}, {"name": "TCD2_SLAST", "offset": "0x104c"}, {"name": "TCD3_SLAST", "offset": "0x106c"}, {"name": "TCD4_SLAST", "offset": "0x108c"}, {"name": "TCD5_SLAST", "offset": "0x10ac"}, {"name": "TCD6_SLAST", "offset": "0x10cc"}, {"name": "TCD7_SLAST", "offset": "0x10ec"}, {"name": "TCD8_SLAST", "offset": "0x110c"}, {"name": "TCD9_SLAST", "offset": "0x112c"}, {"name": "TCD10_SLAST", "offset": "0x114c"}, {"name": "TCD11_SLAST", "offset": "0x116c"}, {"name": "TCD12_SLAST", "offset": "0x118c"}, {"name": "TCD13_SLAST", "offset": "0x11ac"}, {"name": "TCD14_SLAST", "offset": "0x11cc"}, {"name": "TCD15_SLAST", "offset": "0x11ec"}, {"name": "TCD0_DADDR", "offset": "0x1010"}, {"name": "TCD1_DADDR", "offset": "0x1030"}, {"name": "TCD2_DADDR", "offset": "0x1050"}, {"name": "TCD3_DADDR", "offset": "0x1070"}, {"name": "TCD4_DADDR", "offset": "0x1090"}, {"name": "TCD5_DADDR", "offset": "0x10b0"}, {"name": "TCD6_DADDR", "offset": "0x10d0"}, {"name": "TCD7_DADDR", "offset": "0x10f0"}, {"name": "TCD8_DADDR", "offset": "0x1110"}, {"name": "TCD9_DADDR", "offset": "0x1130"}, {"name": "TCD10_DADDR", "offset": "0x1150"}, {"name": "TCD11_DADDR", "offset": "0x1170"}, {"name": "TCD12_DADDR", "offset": "0x1190"}, {"name": "TCD13_DADDR", "offset": "0x11b0"}, {"name": "TCD14_DADDR", "offset": "0x11d0"}, {"name": "TCD15_DADDR", "offset": "0x11f0"}, {"name": "TCD0_DOFF", "offset": "0x1014", "size": "0x10"}, {"name": "TCD1_DOFF", "offset": "0x1034", "size": "0x10"}, {"name": "TCD2_DOFF", "offset": "0x1054", "size": "0x10"}, {"name": "TCD3_DOFF", "offset": "0x1074", "size": "0x10"}, {"name": "TCD4_DOFF", "offset": "0x1094", "size": "0x10"}, {"name": "TCD5_DOFF", "offset": "0x10b4", "size": "0x10"}, {"name": "TCD6_DOFF", "offset": "0x10d4", "size": "0x10"}, {"name": "TCD7_DOFF", "offset": "0x10f4", "size": "0x10"}, {"name": "TCD8_DOFF", "offset": "0x1114", "size": "0x10"}, {"name": "TCD9_DOFF", "offset": "0x1134", "size": "0x10"}, {"name": "TCD10_DOFF", "offset": "0x1154", "size": "0x10"}, {"name": "TCD11_DOFF", "offset": "0x1174", "size": "0x10"}, {"name": "TCD12_DOFF", "offset": "0x1194", "size": "0x10"}, {"name": "TCD13_DOFF", "offset": "0x11b4", "size": "0x10"}, {"name": "TCD14_DOFF", "offset": "0x11d4", "size": "0x10"}, {"name": "TCD15_DOFF", "offset": "0x11f4", "size": "0x10"}, {"name": "TCD0_CITER_ELINKNO", "offset": "0x1016", "size": "0x10"}, {"name": "TCD1_CITER_ELINKNO", "offset": "0x1036", "size": "0x10"}, {"name": "TCD2_CITER_ELINKNO", "offset": "0x1056", "size": "0x10"}, {"name": "TCD3_CITER_ELINKNO", "offset": "0x1076", "size": "0x10"}, {"name": "TCD4_CITER_ELINKNO", "offset": "0x1096", "size": "0x10"}, {"name": "TCD5_CITER_ELINKNO", "offset": "0x10b6", "size": "0x10"}, {"name": "TCD6_CITER_ELINKNO", "offset": "0x10d6", "size": "0x10"}, {"name": "TCD7_CITER_ELINKNO", "offset": "0x10f6", "size": "0x10"}, {"name": "TCD8_CITER_ELINKNO", "offset": "0x1116", "size": "0x10"}, {"name": "TCD9_CITER_ELINKNO", "offset": "0x1136", "size": "0x10"}, {"name": "TCD10_CITER_ELINKNO", "offset": "0x1156", "size": "0x10"}, {"name": "TCD11_CITER_ELINKNO", "offset": "0x1176", "size": "0x10"}, {"name": "TCD12_CITER_ELINKNO", "offset": "0x1196", "size": "0x10"}, {"name": "TCD13_CITER_ELINKNO", "offset": "0x11b6", "size": "0x10"}, {"name": "TCD14_CITER_ELINKNO", "offset": "0x11d6", "size": "0x10"}, {"name": "TCD15_CITER_ELINKNO", "offset": "0x11f6", "size": "0x10"}, {"name": "TCD0_CITER_ELINKYES", "offset": "0x1016", "size": "0x10"}, {"name": "TCD1_CITER_ELINKYES", "offset": "0x1036", "size": "0x10"}, {"name": "TCD2_CITER_ELINKYES", "offset": "0x1056", "size": "0x10"}, {"name": "TCD3_CITER_ELINKYES", "offset": "0x1076", "size": "0x10"}, {"name": "TCD4_CITER_ELINKYES", "offset": "0x1096", "size": "0x10"}, {"name": "TCD5_CITER_ELINKYES", "offset": "0x10b6", "size": "0x10"}, {"name": "TCD6_CITER_ELINKYES", "offset": "0x10d6", "size": "0x10"}, {"name": "TCD7_CITER_ELINKYES", "offset": "0x10f6", "size": "0x10"}, {"name": "TCD8_CITER_ELINKYES", "offset": "0x1116", "size": "0x10"}, {"name": "TCD9_CITER_ELINKYES", "offset": "0x1136", "size": "0x10"}, {"name": "TCD10_CITER_ELINKYES", "offset": "0x1156", "size": "0x10"}, {"name": "TCD11_CITER_ELINKYES", "offset": "0x1176", "size": "0x10"}, {"name": "TCD12_CITER_ELINKYES", "offset": "0x1196", "size": "0x10"}, {"name": "TCD13_CITER_ELINKYES", "offset": "0x11b6", "size": "0x10"}, {"name": "TCD14_CITER_ELINKYES", "offset": "0x11d6", "size": "0x10"}, {"name": "TCD15_CITER_ELINKYES", "offset": "0x11f6", "size": "0x10"}, {"name": "TCD0_DLASTSGA", "offset": "0x1018"}, {"name": "TCD1_DLASTSGA", "offset": "0x1038"}, {"name": "TCD2_DLASTSGA", "offset": "0x1058"}, {"name": "TCD3_DLASTSGA", "offset": "0x1078"}, {"name": "TCD4_DLASTSGA", "offset": "0x1098"}, {"name": "TCD5_DLASTSGA", "offset": "0x10b8"}, {"name": "TCD6_DLASTSGA", "offset": "0x10d8"}, {"name": "TCD7_DLASTSGA", "offset": "0x10f8"}, {"name": "TCD8_DLASTSGA", "offset": "0x1118"}, {"name": "TCD9_DLASTSGA", "offset": "0x1138"}, {"name": "TCD10_DLASTSGA", "offset": "0x1158"}, {"name": "TCD11_DLASTSGA", "offset": "0x1178"}, {"name": "TCD12_DLASTSGA", "offset": "0x1198"}, {"name": "TCD13_DLASTSGA", "offset": "0x11b8"}, {"name": "TCD14_DLASTSGA", "offset": "0x11d8"}, {"name": "TCD15_DLASTSGA", "offset": "0x11f8"}, {"name": "TCD0_CSR", "offset": "0x101c", "size": "0x10"}, {"name": "TCD1_CSR", "offset": "0x103c", "size": "0x10"}, {"name": "TCD2_CSR", "offset": "0x105c", "size": "0x10"}, {"name": "TCD3_CSR", "offset": "0x107c", "size": "0x10"}, {"name": "TCD4_CSR", "offset": "0x109c", "size": "0x10"}, {"name": "TCD5_CSR", "offset": "0x10bc", "size": "0x10"}, {"name": "TCD6_CSR", "offset": "0x10dc", "size": "0x10"}, {"name": "TCD7_CSR", "offset": "0x10fc", "size": "0x10"}, {"name": "TCD8_CSR", "offset": "0x111c", "size": "0x10"}, {"name": "TCD9_CSR", "offset": "0x113c", "size": "0x10"}, {"name": "TCD10_CSR", "offset": "0x115c", "size": "0x10"}, {"name": "TCD11_CSR", "offset": "0x117c", "size": "0x10"}, {"name": "TCD12_CSR", "offset": "0x119c", "size": "0x10"}, {"name": "TCD13_CSR", "offset": "0x11bc", "size": "0x10"}, {"name": "TCD14_CSR", "offset": "0x11dc", "size": "0x10"}, {"name": "TCD15_CSR", "offset": "0x11fc", "size": "0x10"}, {"name": "TCD0_BITER_ELINKNO", "offset": "0x101e", "size": "0x10"}, {"name": "TCD1_BITER_ELINKNO", "offset": "0x103e", "size": "0x10"}, {"name": "TCD2_BITER_ELINKNO", "offset": "0x105e", "size": "0x10"}, {"name": "TCD3_BITER_ELINKNO", "offset": "0x107e", "size": "0x10"}, {"name": "TCD4_BITER_ELINKNO", "offset": "0x109e", "size": "0x10"}, {"name": "TCD5_BITER_ELINKNO", "offset": "0x10be", "size": "0x10"}, {"name": "TCD6_BITER_ELINKNO", "offset": "0x10de", "size": "0x10"}, {"name": "TCD7_BITER_ELINKNO", "offset": "0x10fe", "size": "0x10"}, {"name": "TCD8_BITER_ELINKNO", "offset": "0x111e", "size": "0x10"}, {"name": "TCD9_BITER_ELINKNO", "offset": "0x113e", "size": "0x10"}, {"name": "TCD10_BITER_ELINKNO", "offset": "0x115e", "size": "0x10"}, {"name": "TCD11_BITER_ELINKNO", "offset": "0x117e", "size": "0x10"}, {"name": "TCD12_BITER_ELINKNO", "offset": "0x119e", "size": "0x10"}, {"name": "TCD13_BITER_ELINKNO", "offset": "0x11be", "size": "0x10"}, {"name": "TCD14_BITER_ELINKNO", "offset": "0x11de", "size": "0x10"}, {"name": "TCD15_BITER_ELINKNO", "offset": "0x11fe", "size": "0x10"}, {"name": "TCD0_BITER_ELINKYES", "offset": "0x101e", "size": "0x10"}, {"name": "TCD1_BITER_ELINKYES", "offset": "0x103e", "size": "0x10"}, {"name": "TCD2_BITER_ELINKYES", "offset": "0x105e", "size": "0x10"}, {"name": "TCD3_BITER_ELINKYES", "offset": "0x107e", "size": "0x10"}, {"name": "TCD4_BITER_ELINKYES", "offset": "0x109e", "size": "0x10"}, {"name": "TCD5_BITER_ELINKYES", "offset": "0x10be", "size": "0x10"}, {"name": "TCD6_BITER_ELINKYES", "offset": "0x10de", "size": "0x10"}, {"name": "TCD7_BITER_ELINKYES", "offset": "0x10fe", "size": "0x10"}, {"name": "TCD8_BITER_ELINKYES", "offset": "0x111e", "size": "0x10"}, {"name": "TCD9_BITER_ELINKYES", "offset": "0x113e", "size": "0x10"}, {"name": "TCD10_BITER_ELINKYES", "offset": "0x115e", "size": "0x10"}, {"name": "TCD11_BITER_ELINKYES", "offset": "0x117e", "size": "0x10"}, {"name": "TCD12_BITER_ELINKYES", "offset": "0x119e", "size": "0x10"}, {"name": "TCD13_BITER_ELINKYES", "offset": "0x11be", "size": "0x10"}, {"name": "TCD14_BITER_ELINKYES", "offset": "0x11de", "size": "0x10"}, {"name": "TCD15_BITER_ELINKYES", "offset": "0x11fe", "size": "0x10"}]}, {"name": "FB", "start": "0x4000c000", "end": "0x4000c063", "size": "0x64", "comment": "", "registers": [{"name": "CSPMCR", "offset": "0x60"}, {"name": "CSAR0", "offset": "0x0"}, {"name": "CSAR1", "offset": "0xc"}, {"name": "CSAR2", "offset": "0x18"}, {"name": "CSAR3", "offset": "0x24"}, {"name": "CSAR4", "offset": "0x30"}, {"name": "CSAR5", "offset": "0x3c"}, {"name": "CSMR0", "offset": "0x4"}, {"name": "CSMR1", "offset": "0x10"}, {"name": "CSMR2", "offset": "0x1c"}, {"name": "CSMR3", "offset": "0x28"}, {"name": "CSMR4", "offset": "0x34"}, {"name": "CSMR5", "offset": "0x40"}, {"name": "CSCR0", "offset": "0x8"}, {"name": "CSCR1", "offset": "0x14"}, {"name": "CSCR2", "offset": "0x20"}, {"name": "CSCR3", "offset": "0x2c"}, {"name": "CSCR4", "offset": "0x38"}, {"name": "CSCR5", "offset": "0x44"}]}, {"name": "MPU", "start": "0x4000d000", "end": "0x4000d82f", "size": "0x830", "comment": "", "registers": [{"name": "CESR", "offset": "0x0"}, {"name": "EAR0", "offset": "0x10"}, {"name": "EAR1", "offset": "0x18"}, {"name": "EAR2", "offset": "0x20"}, {"name": "EAR3", "offset": "0x28"}, {"name": "EAR4", "offset": "0x30"}, {"name": "EDR0", "offset": "0x14"}, {"name": "EDR1", "offset": "0x1c"}, {"name": "EDR2", "offset": "0x24"}, {"name": "EDR3", "offset": "0x2c"}, {"name": "EDR4", "offset": "0x34"}, {"name": "RGD0_WORD0", "offset": "0x400"}, {"name": "RGD1_WORD0", "offset": "0x410"}, {"name": "RGD2_WORD0", "offset": "0x420"}, {"name": "RGD3_WORD0", "offset": "0x430"}, {"name": "RGD4_WORD0", "offset": "0x440"}, {"name": "RGD5_WORD0", "offset": "0x450"}, {"name": "RGD6_WORD0", "offset": "0x460"}, {"name": "RGD7_WORD0", "offset": "0x470"}, {"name": "RGD8_WORD0", "offset": "0x480"}, {"name": "RGD9_WORD0", "offset": "0x490"}, {"name": "RGD10_WORD0", "offset": "0x4a0"}, {"name": "RGD11_WORD0", "offset": "0x4b0"}, {"name": "RGD0_WORD1", "offset": "0x404"}, {"name": "RGD1_WORD1", "offset": "0x414"}, {"name": "RGD2_WORD1", "offset": "0x424"}, {"name": "RGD3_WORD1", "offset": "0x434"}, {"name": "RGD4_WORD1", "offset": "0x444"}, {"name": "RGD5_WORD1", "offset": "0x454"}, {"name": "RGD6_WORD1", "offset": "0x464"}, {"name": "RGD7_WORD1", "offset": "0x474"}, {"name": "RGD8_WORD1", "offset": "0x484"}, {"name": "RGD9_WORD1", "offset": "0x494"}, {"name": "RGD10_WORD1", "offset": "0x4a4"}, {"name": "RGD11_WORD1", "offset": "0x4b4"}, {"name": "RGD0_WORD2", "offset": "0x408"}, {"name": "RGD1_WORD2", "offset": "0x418"}, {"name": "RGD2_WORD2", "offset": "0x428"}, {"name": "RGD3_WORD2", "offset": "0x438"}, {"name": "RGD4_WORD2", "offset": "0x448"}, {"name": "RGD5_WORD2", "offset": "0x458"}, {"name": "RGD6_WORD2", "offset": "0x468"}, {"name": "RGD7_WORD2", "offset": "0x478"}, {"name": "RGD8_WORD2", "offset": "0x488"}, {"name": "RGD9_WORD2", "offset": "0x498"}, {"name": "RGD10_WORD2", "offset": "0x4a8"}, {"name": "RGD11_WORD2", "offset": "0x4b8"}, {"name": "RGD0_WORD3", "offset": "0x40c"}, {"name": "RGD1_WORD3", "offset": "0x41c"}, {"name": "RGD2_WORD3", "offset": "0x42c"}, {"name": "RGD3_WORD3", "offset": "0x43c"}, {"name": "RGD4_WORD3", "offset": "0x44c"}, {"name": "RGD5_WORD3", "offset": "0x45c"}, {"name": "RGD6_WORD3", "offset": "0x46c"}, {"name": "RGD7_WORD3", "offset": "0x47c"}, {"name": "RGD8_WORD3", "offset": "0x48c"}, {"name": "RGD9_WORD3", "offset": "0x49c"}, {"name": "RGD10_WORD3", "offset": "0x4ac"}, {"name": "RGD11_WORD3", "offset": "0x4bc"}, {"name": "RGDAAC0", "offset": "0x800"}, {"name": "RGDAAC1", "offset": "0x804"}, {"name": "RGDAAC2", "offset": "0x808"}, {"name": "RGDAAC3", "offset": "0x80c"}, {"name": "RGDAAC4", "offset": "0x810"}, {"name": "RGDAAC5", "offset": "0x814"}, {"name": "RGDAAC6", "offset": "0x818"}, {"name": "RGDAAC7", "offset": "0x81c"}, {"name": "RGDAAC8", "offset": "0x820"}, {"name": "RGDAAC9", "offset": "0x824"}, {"name": "RGDAAC10", "offset": "0x828"}, {"name": "RGDAAC11", "offset": "0x82c"}]}, {"name": "FMC", "start": "0x4001f000", "end": "0x4001f2ff", "size": "0x300", "comment": "", "registers": [{"name": "PFAPR", "offset": "0x0"}, {"name": "PFB0CR", "offset": "0x4"}, {"name": "PFB1CR", "offset": "0x8"}, {"name": "TAGVDW0S0", "offset": "0x100"}, {"name": "TAGVDW0S1", "offset": "0x104"}, {"name": "TAGVDW0S2", "offset": "0x108"}, {"name": "TAGVDW0S3", "offset": "0x10c"}, {"name": "TAGVDW0S4", "offset": "0x110"}, {"name": "TAGVDW0S5", "offset": "0x114"}, {"name": "TAGVDW0S6", "offset": "0x118"}, {"name": "TAGVDW0S7", "offset": "0x11c"}, {"name": "TAGVDW1S0", "offset": "0x120"}, {"name": "TAGVDW1S1", "offset": "0x124"}, {"name": "TAGVDW1S2", "offset": "0x128"}, {"name": "TAGVDW1S3", "offset": "0x12c"}, {"name": "TAGVDW1S4", "offset": "0x130"}, {"name": "TAGVDW1S5", "offset": "0x134"}, {"name": "TAGVDW1S6", "offset": "0x138"}, {"name": "TAGVDW1S7", "offset": "0x13c"}, {"name": "TAGVDW2S0", "offset": "0x140"}, {"name": "TAGVDW2S1", "offset": "0x144"}, {"name": "TAGVDW2S2", "offset": "0x148"}, {"name": "TAGVDW2S3", "offset": "0x14c"}, {"name": "TAGVDW2S4", "offset": "0x150"}, {"name": "TAGVDW2S5", "offset": "0x154"}, {"name": "TAGVDW2S6", "offset": "0x158"}, {"name": "TAGVDW2S7", "offset": "0x15c"}, {"name": "TAGVDW3S0", "offset": "0x160"}, {"name": "TAGVDW3S1", "offset": "0x164"}, {"name": "TAGVDW3S2", "offset": "0x168"}, {"name": "TAGVDW3S3", "offset": "0x16c"}, {"name": "TAGVDW3S4", "offset": "0x170"}, {"name": "TAGVDW3S5", "offset": "0x174"}, {"name": "TAGVDW3S6", "offset": "0x178"}, {"name": "TAGVDW3S7", "offset": "0x17c"}, {"name": "DATAW0S0U", "offset": "0x200"}, {"name": "DATAW0S1U", "offset": "0x208"}, {"name": "DATAW0S2U", "offset": "0x210"}, {"name": "DATAW0S3U", "offset": "0x218"}, {"name": "DATAW0S4U", "offset": "0x220"}, {"name": "DATAW0S5U", "offset": "0x228"}, {"name": "DATAW0S6U", "offset": "0x230"}, {"name": "DATAW0S7U", "offset": "0x238"}, {"name": "DATAW0S0L", "offset": "0x204"}, {"name": "DATAW0S1L", "offset": "0x20c"}, {"name": "DATAW0S2L", "offset": "0x214"}, {"name": "DATAW0S3L", "offset": "0x21c"}, {"name": "DATAW0S4L", "offset": "0x224"}, {"name": "DATAW0S5L", "offset": "0x22c"}, {"name": "DATAW0S6L", "offset": "0x234"}, {"name": "DATAW0S7L", "offset": "0x23c"}, {"name": "DATAW1S0U", "offset": "0x240"}, {"name": "DATAW1S1U", "offset": "0x248"}, {"name": "DATAW1S2U", "offset": "0x250"}, {"name": "DATAW1S3U", "offset": "0x258"}, {"name": "DATAW1S4U", "offset": "0x260"}, {"name": "DATAW1S5U", "offset": "0x268"}, {"name": "DATAW1S6U", "offset": "0x270"}, {"name": "DATAW1S7U", "offset": "0x278"}, {"name": "DATAW1S0L", "offset": "0x244"}, {"name": "DATAW1S1L", "offset": "0x24c"}, {"name": "DATAW1S2L", "offset": "0x254"}, {"name": "DATAW1S3L", "offset": "0x25c"}, {"name": "DATAW1S4L", "offset": "0x264"}, {"name": "DATAW1S5L", "offset": "0x26c"}, {"name": "DATAW1S6L", "offset": "0x274"}, {"name": "DATAW1S7L", "offset": "0x27c"}, {"name": "DATAW2S0U", "offset": "0x280"}, {"name": "DATAW2S1U", "offset": "0x288"}, {"name": "DATAW2S2U", "offset": "0x290"}, {"name": "DATAW2S3U", "offset": "0x298"}, {"name": "DATAW2S4U", "offset": "0x2a0"}, {"name": "DATAW2S5U", "offset": "0x2a8"}, {"name": "DATAW2S6U", "offset": "0x2b0"}, {"name": "DATAW2S7U", "offset": "0x2b8"}, {"name": "DATAW2S0L", "offset": "0x284"}, {"name": "DATAW2S1L", "offset": "0x28c"}, {"name": "DATAW2S2L", "offset": "0x294"}, {"name": "DATAW2S3L", "offset": "0x29c"}, {"name": "DATAW2S4L", "offset": "0x2a4"}, {"name": "DATAW2S5L", "offset": "0x2ac"}, {"name": "DATAW2S6L", "offset": "0x2b4"}, {"name": "DATAW2S7L", "offset": "0x2bc"}, {"name": "DATAW3S0U", "offset": "0x2c0"}, {"name": "DATAW3S1U", "offset": "0x2c8"}, {"name": "DATAW3S2U", "offset": "0x2d0"}, {"name": "DATAW3S3U", "offset": "0x2d8"}, {"name": "DATAW3S4U", "offset": "0x2e0"}, {"name": "DATAW3S5U", "offset": "0x2e8"}, {"name": "DATAW3S6U", "offset": "0x2f0"}, {"name": "DATAW3S7U", "offset": "0x2f8"}, {"name": "DATAW3S0L", "offset": "0x2c4"}, {"name": "DATAW3S1L", "offset": "0x2cc"}, {"name": "DATAW3S2L", "offset": "0x2d4"}, {"name": "DATAW3S3L", "offset": "0x2dc"}, {"name": "DATAW3S4L", "offset": "0x2e4"}, {"name": "DATAW3S5L", "offset": "0x2ec"}, {"name": "DATAW3S6L", "offset": "0x2f4"}, {"name": "DATAW3S7L", "offset": "0x2fc"}]}, {"name": "FTFL", "start": "0x40020000", "end": "0x40020013", "size": "0x14", "comment": "", "registers": [{"name": "FSTAT", "offset": "0x0", "size": "0x8"}, {"name": "FCNFG", "offset": "0x1", "size": "0x8"}, {"name": "FSEC", "offset": "0x2", "size": "0x8"}, {"name": "FOPT", "offset": "0x3", "size": "0x8"}, {"name": "FCCOB3", "offset": "0x4", "size": "0x8"}, {"name": "FCCOB2", "offset": "0x5", "size": "0x8"}, {"name": "FCCOB1", "offset": "0x6", "size": "0x8"}, {"name": "FCCOB0", "offset": "0x7", "size": "0x8"}, {"name": "FCCOB7", "offset": "0x8", "size": "0x8"}, {"name": "FCCOB6", "offset": "0x9", "size": "0x8"}, {"name": "FCCOB5", "offset": "0xa", "size": "0x8"}, {"name": "FCCOB4", "offset": "0xb", "size": "0x8"}, {"name": "FCCOBB", "offset": "0xc", "size": "0x8"}, {"name": "FCCOBA", "offset": "0xd", "size": "0x8"}, {"name": "FCCOB9", "offset": "0xe", "size": "0x8"}, {"name": "FCCOB8", "offset": "0xf", "size": "0x8"}, {"name": "FPROT3", "offset": "0x10", "size": "0x8"}, {"name": "FPROT2", "offset": "0x11", "size": "0x8"}, {"name": "FPROT1", "offset": "0x12", "size": "0x8"}, {"name": "FPROT0", "offset": "0x13", "size": "0x8"}]}, {"name": "DMAMUX", "start": "0x40021000", "end": "0x4002100f", "size": "0x10", "comment": "", "registers": [{"name": "CHCFG0", "offset": "0x0", "size": "0x8"}, {"name": "CHCFG1", "offset": "0x1", "size": "0x8"}, {"name": "CHCFG2", "offset": "0x2", "size": "0x8"}, {"name": "CHCFG3", "offset": "0x3", "size": "0x8"}, {"name": "CHCFG4", "offset": "0x4", "size": "0x8"}, {"name": "CHCFG5", "offset": "0x5", "size": "0x8"}, {"name": "CHCFG6", "offset": "0x6", "size": "0x8"}, {"name": "CHCFG7", "offset": "0x7", "size": "0x8"}, {"name": "CHCFG8", "offset": "0x8", "size": "0x8"}, {"name": "CHCFG9", "offset": "0x9", "size": "0x8"}, {"name": "CHCFG10", "offset": "0xa", "size": "0x8"}, {"name": "CHCFG11", "offset": "0xb", "size": "0x8"}, {"name": "CHCFG12", "offset": "0xc", "size": "0x8"}, {"name": "CHCFG13", "offset": "0xd", "size": "0x8"}, {"name": "CHCFG14", "offset": "0xe", "size": "0x8"}, {"name": "CHCFG15", "offset": "0xf", "size": "0x8"}]}, {"name": "SPI0", "start": "0x4002c000", "end": "0x4002c08b", "size": "0x8c", "comment": "", "registers": [{"name": "MCR", "offset": "0x0"}, {"name": "TCR", "offset": "0x8"}, {"name": "CTAR_SLAVE", "offset": "0xc"}, {"name": "SR", "offset": "0x2c"}, {"name": "RSER", "offset": "0x30"}, {"name": "PUSHR", "offset": "0x34"}, {"name": "PUSHR_SLAVE", "offset": "0x34"}, {"name": "POPR", "offset": "0x38"}, {"name": "CTAR0", "offset": "0xc"}, {"name": "CTAR1", "offset": "0x10"}, {"name": "TXFR0", "offset": "0x3c"}, {"name": "TXFR1", "offset": "0x40"}, {"name": "TXFR2", "offset": "0x44"}, {"name": "TXFR3", "offset": "0x48"}, {"name": "RXFR0", "offset": "0x7c"}, {"name": "RXFR1", "offset": "0x80"}, {"name": "RXFR2", "offset": "0x84"}, {"name": "RXFR3", "offset": "0x88"}]}, {"name": "SPI1", "start": "0x4002d000", "end": "0x4002d08b", "size": "0x8c", "comment": "", "registers": [{"name": "MCR", "offset": "0x0"}, {"name": "TCR", "offset": "0x8"}, {"name": "CTAR_SLAVE", "offset": "0xc"}, {"name": "SR", "offset": "0x2c"}, {"name": "RSER", "offset": "0x30"}, {"name": "PUSHR", "offset": "0x34"}, {"name": "PUSHR_SLAVE", "offset": "0x34"}, {"name": "POPR", "offset": "0x38"}, {"name": "CTAR0", "offset": "0xc"}, {"name": "CTAR1", "offset": "0x10"}, {"name": "TXFR0", "offset": "0x3c"}, {"name": "TXFR1", "offset": "0x40"}, {"name": "TXFR2", "offset": "0x44"}, {"name": "TXFR3", "offset": "0x48"}, {"name": "RXFR0", "offset": "0x7c"}, {"name": "RXFR1", "offset": "0x80"}, {"name": "RXFR2", "offset": "0x84"}, {"name": "RXFR3", "offset": "0x88"}]}, {"name": "SPI2", "start": "0x400ac000", "end": "0x400ac08b", "size": "0x8c", "comment": "", "registers": [{"name": "MCR", "offset": "0x0"}, {"name": "TCR", "offset": "0x8"}, {"name": "CTAR_SLAVE", "offset": "0xc"}, {"name": "SR", "offset": "0x2c"}, {"name": "RSER", "offset": "0x30"}, {"name": "PUSHR", "offset": "0x34"}, {"name": "PUSHR_SLAVE", "offset": "0x34"}, {"name": "POPR", "offset": "0x38"}, {"name": "CTAR0", "offset": "0xc"}, {"name": "CTAR1", "offset": "0x10"}, {"name": "TXFR0", "offset": "0x3c"}, {"name": "TXFR1", "offset": "0x40"}, {"name": "TXFR2", "offset": "0x44"}, {"name": "TXFR3", "offset": "0x48"}, {"name": "RXFR0", "offset": "0x7c"}, {"name": "RXFR1", "offset": "0x80"}, {"name": "RXFR2", "offset": "0x84"}, {"name": "RXFR3", "offset": "0x88"}]}, {"name": "I2S0", "start": "0x4002f000", "end": "0x4002f107", "size": "0x108", "comment": "", "registers": [{"name": "TCSR", "offset": "0x0"}, {"name": "TCR1", "offset": "0x4"}, {"name": "TCR2", "offset": "0x8"}, {"name": "TCR3", "offset": "0xc"}, {"name": "TCR4", "offset": "0x10"}, {"name": "TCR5", "offset": "0x14"}, {"name": "TMR", "offset": "0x60"}, {"name": "RCSR", "offset": "0x80"}, {"name": "RCR1", "offset": "0x84"}, {"name": "RCR2", "offset": "0x88"}, {"name": "RCR3", "offset": "0x8c"}, {"name": "RCR4", "offset": "0x90"}, {"name": "RCR5", "offset": "0x94"}, {"name": "RMR", "offset": "0xe0"}, {"name": "MCR", "offset": "0x100"}, {"name": "MDR", "offset": "0x104"}, {"name": "TDR0", "offset": "0x20"}, {"name": "TDR1", "offset": "0x24"}, {"name": "TFR0", "offset": "0x40"}, {"name": "TFR1", "offset": "0x44"}, {"name": "RDR0", "offset": "0xa0"}, {"name": "RDR1", "offset": "0xa4"}, {"name": "RFR0", "offset": "0xc0"}, {"name": "RFR1", "offset": "0xc4"}]}, {"name": "CRC", "start": "0x40032000", "end": "0x4003200b", "size": "0xc", "comment": "", "registers": [{"name": "CRC", "offset": "0x0"}, {"name": "CRCL", "offset": "0x0", "size": "0x10"}, {"name": "CRCLL", "offset": "0x0", "size": "0x8"}, {"name": "CRCLU", "offset": "0x1", "size": "0x8"}, {"name": "CRCH", "offset": "0x2", "size": "0x10"}, {"name": "CRCHL", "offset": "0x2", "size": "0x8"}, {"name": "CRCHU", "offset": "0x3", "size": "0x8"}, {"name": "GPOLY", "offset": "0x4"}, {"name": "GPOLYL", "offset": "0x4", "size": "0x10"}, {"name": "GPOLYLL", "offset": "0x4", "size": "0x8"}, {"name": "GPOLYLU", "offset": "0x5", "size": "0x8"}, {"name": "GPOLYH", "offset": "0x6", "size": "0x10"}, {"name": "GPOLYHL", "offset": "0x6", "size": "0x8"}, {"name": "GPOLYHU", "offset": "0x7", "size": "0x8"}, {"name": "CTRL", "offset": "0x8"}, {"name": "CTRLHU", "offset": "0xb", "size": "0x8"}]}, {"name": "USBDCD", "start": "0x40035000", "end": "0x4003501b", "size": "0x1c", "comment": "", "registers": [{"name": "CONTROL", "offset": "0x0"}, {"name": "CLOCK", "offset": "0x4"}, {"name": "STATUS", "offset": "0x8"}, {"name": "TIMER0", "offset": "0x10"}, {"name": "TIMER1", "offset": "0x14"}, {"name": "TIMER2", "offset": "0x18"}]}, {"name": "PDB0", "start": "0x40036000", "end": "0x4003619f", "size": "0x1a0", "comment": "", "registers": [{"name": "SC", "offset": "0x0"}, {"name": "MOD", "offset": "0x4"}, {"name": "CNT", "offset": "0x8"}, {"name": "IDLY", "offset": "0xc"}, {"name": "POEN", "offset": "0x190"}, {"name": "CH0C1", "offset": "0x10"}, {"name": "CH1C1", "offset": "0x38"}, {"name": "CH0S", "offset": "0x14"}, {"name": "CH1S", "offset": "0x3c"}, {"name": "CH0DLY0", "offset": "0x18"}, {"name": "CH1DLY0", "offset": "0x40"}, {"name": "CH0DLY1", "offset": "0x1c"}, {"name": "CH1DLY1", "offset": "0x44"}, {"name": "DACINTC0", "offset": "0x150"}, {"name": "DACINTC1", "offset": "0x158"}, {"name": "DACINT0", "offset": "0x154"}, {"name": "DACINT1", "offset": "0x15c"}, {"name": "PO0DLY", "offset": "0x194"}, {"name": "PO1DLY", "offset": "0x198"}, {"name": "PO2DLY", "offset": "0x19c"}]}, {"name": "PIT", "start": "0x40037000", "end": "0x4003713f", "size": "0x140", "comment": "", "registers": [{"name": "MCR", "offset": "0x0"}, {"name": "LDVAL0", "offset": "0x100"}, {"name": "LDVAL1", "offset": "0x110"}, {"name": "LDVAL2", "offset": "0x120"}, {"name": "LDVAL3", "offset": "0x130"}, {"name": "CVAL0", "offset": "0x104"}, {"name": "CVAL1", "offset": "0x114"}, {"name": "CVAL2", "offset": "0x124"}, {"name": "CVAL3", "offset": "0x134"}, {"name": "TCTRL0", "offset": "0x108"}, {"name": "TCTRL1", "offset": "0x118"}, {"name": "TCTRL2", "offset": "0x128"}, {"name": "TCTRL3", "offset": "0x138"}, {"name": "TFLG0", "offset": "0x10c"}, {"name": "TFLG1", "offset": "0x11c"}, {"name": "TFLG2", "offset": "0x12c"}, {"name": "TFLG3", "offset": "0x13c"}]}, {"name": "FTM0", "start": "0x40038000", "end": "0x4003809b", "size": "0x9c", "comment": "", "registers": [{"name": "SC", "offset": "0x0"}, {"name": "CNT", "offset": "0x4"}, {"name": "MOD", "offset": "0x8"}, {"name": "CNTIN", "offset": "0x4c"}, {"name": "STATUS", "offset": "0x50"}, {"name": "MODE", "offset": "0x54"}, {"name": "SYNC", "offset": "0x58"}, {"name": "OUTINIT", "offset": "0x5c"}, {"name": "OUTMASK", "offset": "0x60"}, {"name": "COMBINE", "offset": "0x64"}, {"name": "DEADTIME", "offset": "0x68"}, {"name": "EXTTRIG", "offset": "0x6c"}, {"name": "POL", "offset": "0x70"}, {"name": "FMS", "offset": "0x74"}, {"name": "FILTER", "offset": "0x78"}, {"name": "FLTCTRL", "offset": "0x7c"}, {"name": "QDCTRL", "offset": "0x80"}, {"name": "CONF", "offset": "0x84"}, {"name": "FLTPOL", "offset": "0x88"}, {"name": "SYNCONF", "offset": "0x8c"}, {"name": "INVCTRL", "offset": "0x90"}, {"name": "SWOCTRL", "offset": "0x94"}, {"name": "PWMLOAD", "offset": "0x98"}, {"name": "C0SC", "offset": "0xc"}, {"name": "C1SC", "offset": "0x14"}, {"name": "C2SC", "offset": "0x1c"}, {"name": "C3SC", "offset": "0x24"}, {"name": "C4SC", "offset": "0x2c"}, {"name": "C5SC", "offset": "0x34"}, {"name": "C6SC", "offset": "0x3c"}, {"name": "C7SC", "offset": "0x44"}, {"name": "C0V", "offset": "0x10"}, {"name": "C1V", "offset": "0x18"}, {"name": "C2V", "offset": "0x20"}, {"name": "C3V", "offset": "0x28"}, {"name": "C4V", "offset": "0x30"}, {"name": "C5V", "offset": "0x38"}, {"name": "C6V", "offset": "0x40"}, {"name": "C7V", "offset": "0x48"}]}, {"name": "FTM1", "start": "0x40039000", "end": "0x4003909b", "size": "0x9c", "comment": "", "registers": [{"name": "SC", "offset": "0x0"}, {"name": "CNT", "offset": "0x4"}, {"name": "MOD", "offset": "0x8"}, {"name": "CNTIN", "offset": "0x4c"}, {"name": "STATUS", "offset": "0x50"}, {"name": "MODE", "offset": "0x54"}, {"name": "SYNC", "offset": "0x58"}, {"name": "OUTINIT", "offset": "0x5c"}, {"name": "OUTMASK", "offset": "0x60"}, {"name": "COMBINE", "offset": "0x64"}, {"name": "DEADTIME", "offset": "0x68"}, {"name": "EXTTRIG", "offset": "0x6c"}, {"name": "POL", "offset": "0x70"}, {"name": "FMS", "offset": "0x74"}, {"name": "FILTER", "offset": "0x78"}, {"name": "FLTCTRL", "offset": "0x7c"}, {"name": "QDCTRL", "offset": "0x80"}, {"name": "CONF", "offset": "0x84"}, {"name": "FLTPOL", "offset": "0x88"}, {"name": "SYNCONF", "offset": "0x8c"}, {"name": "INVCTRL", "offset": "0x90"}, {"name": "SWOCTRL", "offset": "0x94"}, {"name": "PWMLOAD", "offset": "0x98"}, {"name": "C0SC", "offset": "0xc"}, {"name": "C1SC", "offset": "0x14"}, {"name": "C0V", "offset": "0x10"}, {"name": "C1V", "offset": "0x18"}]}, {"name": "FTM2", "start": "0x400b8000", "end": "0x400b809b", "size": "0x9c", "comment": "", "registers": [{"name": "SC", "offset": "0x0"}, {"name": "CNT", "offset": "0x4"}, {"name": "MOD", "offset": "0x8"}, {"name": "CNTIN", "offset": "0x4c"}, {"name": "STATUS", "offset": "0x50"}, {"name": "MODE", "offset": "0x54"}, {"name": "SYNC", "offset": "0x58"}, {"name": "OUTINIT", "offset": "0x5c"}, {"name": "OUTMASK", "offset": "0x60"}, {"name": "COMBINE", "offset": "0x64"}, {"name": "DEADTIME", "offset": "0x68"}, {"name": "EXTTRIG", "offset": "0x6c"}, {"name": "POL", "offset": "0x70"}, {"name": "FMS", "offset": "0x74"}, {"name": "FILTER", "offset": "0x78"}, {"name": "FLTCTRL", "offset": "0x7c"}, {"name": "QDCTRL", "offset": "0x80"}, {"name": "CONF", "offset": "0x84"}, {"name": "FLTPOL", "offset": "0x88"}, {"name": "SYNCONF", "offset": "0x8c"}, {"name": "INVCTRL", "offset": "0x90"}, {"name": "SWOCTRL", "offset": "0x94"}, {"name": "PWMLOAD", "offset": "0x98"}, {"name": "C0SC", "offset": "0xc"}, {"name": "C1SC", "offset": "0x14"}, {"name": "C0V", "offset": "0x10"}, {"name": "C1V", "offset": "0x18"}]}, {"name": "ADC0", "start": "0x4003b000", "end": "0x4003b06f", "size": "0x70", "comment": "", "registers": [{"name": "CFG1", "offset": "0x8"}, {"name": "CFG2", "offset": "0xc"}, {"name": "SC2", "offset": "0x20"}, {"name": "SC3", "offset": "0x24"}, {"name": "OFS", "offset": "0x28"}, {"name": "PG", "offset": "0x2c"}, {"name": "MG", "offset": "0x30"}, {"name": "CLPD", "offset": "0x34"}, {"name": "CLPS", "offset": "0x38"}, {"name": "CLP4", "offset": "0x3c"}, {"name": "CLP3", "offset": "0x40"}, {"name": "CLP2", "offset": "0x44"}, {"name": "CLP1", "offset": "0x48"}, {"name": "CLP0", "offset": "0x4c"}, {"name": "PGA", "offset": "0x50"}, {"name": "CLMD", "offset": "0x54"}, {"name": "CLMS", "offset": "0x58"}, {"name": "CLM4", "offset": "0x5c"}, {"name": "CLM3", "offset": "0x60"}, {"name": "CLM2", "offset": "0x64"}, {"name": "CLM1", "offset": "0x68"}, {"name": "CLM0", "offset": "0x6c"}, {"name": "SC1A", "offset": "0x0"}, {"name": "SC1B", "offset": "0x4"}, {"name": "RA", "offset": "0x10"}, {"name": "RB", "offset": "0x14"}, {"name": "CV1", "offset": "0x18"}, {"name": "CV2", "offset": "0x1c"}]}, {"name": "ADC1", "start": "0x400bb000", "end": "0x400bb06f", "size": "0x70", "comment": "", "registers": [{"name": "CFG1", "offset": "0x8"}, {"name": "CFG2", "offset": "0xc"}, {"name": "SC2", "offset": "0x20"}, {"name": "SC3", "offset": "0x24"}, {"name": "OFS", "offset": "0x28"}, {"name": "PG", "offset": "0x2c"}, {"name": "MG", "offset": "0x30"}, {"name": "CLPD", "offset": "0x34"}, {"name": "CLPS", "offset": "0x38"}, {"name": "CLP4", "offset": "0x3c"}, {"name": "CLP3", "offset": "0x40"}, {"name": "CLP2", "offset": "0x44"}, {"name": "CLP1", "offset": "0x48"}, {"name": "CLP0", "offset": "0x4c"}, {"name": "PGA", "offset": "0x50"}, {"name": "CLMD", "offset": "0x54"}, {"name": "CLMS", "offset": "0x58"}, {"name": "CLM4", "offset": "0x5c"}, {"name": "CLM3", "offset": "0x60"}, {"name": "CLM2", "offset": "0x64"}, {"name": "CLM1", "offset": "0x68"}, {"name": "CLM0", "offset": "0x6c"}, {"name": "SC1A", "offset": "0x0"}, {"name": "SC1B", "offset": "0x4"}, {"name": "RA", "offset": "0x10"}, {"name": "RB", "offset": "0x14"}, {"name": "CV1", "offset": "0x18"}, {"name": "CV2", "offset": "0x1c"}]}, {"name": "RTC", "start": "0x4003d000", "end": "0x4003d807", "size": "0x808", "comment": "", "registers": [{"name": "TSR", "offset": "0x0"}, {"name": "TPR", "offset": "0x4"}, {"name": "TAR", "offset": "0x8"}, {"name": "TCR", "offset": "0xc"}, {"name": "CR", "offset": "0x10"}, {"name": "SR", "offset": "0x14"}, {"name": "LR", "offset": "0x18"}, {"name": "IER", "offset": "0x1c"}, {"name": "WAR", "offset": "0x800"}, {"name": "RAR", "offset": "0x804"}]}, {"name": "RFVBAT", "start": "0x4003e000", "end": "0x4003e01f", "size": "0x20", "comment": "", "registers": [{"name": "REG0", "offset": "0x0"}, {"name": "REG1", "offset": "0x4"}, {"name": "REG2", "offset": "0x8"}, {"name": "REG3", "offset": "0xc"}, {"name": "REG4", "offset": "0x10"}, {"name": "REG5", "offset": "0x14"}, {"name": "REG6", "offset": "0x18"}, {"name": "REG7", "offset": "0x1c"}]}, {"name": "LPTMR0", "start": "0x40040000", "end": "0x4004000f", "size": "0x10", "comment": "", "registers": [{"name": "CSR", "offset": "0x0"}, {"name": "PSR", "offset": "0x4"}, {"name": "CMR", "offset": "0x8"}, {"name": "CNR", "offset": "0xc"}]}, {"name": "RFSYS", "start": "0x40041000", "end": "0x4004101f", "size": "0x20", "comment": "", "registers": [{"name": "REG0", "offset": "0x0"}, {"name": "REG1", "offset": "0x4"}, {"name": "REG2", "offset": "0x8"}, {"name": "REG3", "offset": "0xc"}, {"name": "REG4", "offset": "0x10"}, {"name": "REG5", "offset": "0x14"}, {"name": "REG6", "offset": "0x18"}, {"name": "REG7", "offset": "0x1c"}]}, {"name": "TSI0", "start": "0x40045000", "end": "0x40045123", "size": "0x124", "comment": "", "registers": [{"name": "GENCS", "offset": "0x0"}, {"name": "SCANC", "offset": "0x4"}, {"name": "PEN", "offset": "0x8"}, {"name": "WUCNTR", "offset": "0xc"}, {"name": "THRESHOLD", "offset": "0x120"}, {"name": "CNTR1", "offset": "0x100"}, {"name": "CNTR3", "offset": "0x104"}, {"name": "CNTR5", "offset": "0x108"}, {"name": "CNTR7", "offset": "0x10c"}, {"name": "CNTR9", "offset": "0x110"}, {"name": "CNTR11", "offset": "0x114"}, {"name": "CNTR13", "offset": "0x118"}, {"name": "CNTR15", "offset": "0x11c"}]}, {"name": "SIM", "start": "0x40047000", "end": "0x40048063", "size": "0x1064", "comment": "", "registers": [{"name": "SOPT1", "offset": "0x0"}, {"name": "SOPT1CFG", "offset": "0x4"}, {"name": "SOPT2", "offset": "0x1004"}, {"name": "SOPT4", "offset": "0x100c"}, {"name": "SOPT5", "offset": "0x1010"}, {"name": "SOPT7", "offset": "0x1018"}, {"name": "SDID", "offset": "0x1024"}, {"name": "SCGC1", "offset": "0x1028"}, {"name": "SCGC2", "offset": "0x102c"}, {"name": "SCGC3", "offset": "0x1030"}, {"name": "SCGC4", "offset": "0x1034"}, {"name": "SCGC5", "offset": "0x1038"}, {"name": "SCGC6", "offset": "0x103c"}, {"name": "SCGC7", "offset": "0x1040"}, {"name": "CLKDIV1", "offset": "0x1044"}, {"name": "CLKDIV2", "offset": "0x1048"}, {"name": "FCFG1", "offset": "0x104c"}, {"name": "FCFG2", "offset": "0x1050"}, {"name": "UIDH", "offset": "0x1054"}, {"name": "UIDMH", "offset": "0x1058"}, {"name": "UIDML", "offset": "0x105c"}, {"name": "UIDL", "offset": "0x1060"}]}, {"name": "PORTA", "start": "0x40049000", "end": "0x400490cb", "size": "0xcc", "comment": "", "registers": [{"name": "PCR0", "offset": "0x0"}, {"name": "PCR1", "offset": "0x4"}, {"name": "PCR2", "offset": "0x8"}, {"name": "PCR3", "offset": "0xc"}, {"name": "PCR4", "offset": "0x10"}, {"name": "PCR5", "offset": "0x14"}, {"name": "PCR6", "offset": "0x18"}, {"name": "PCR7", "offset": "0x1c"}, {"name": "PCR8", "offset": "0x20"}, {"name": "PCR9", "offset": "0x24"}, {"name": "PCR10", "offset": "0x28"}, {"name": "PCR11", "offset": "0x2c"}, {"name": "PCR12", "offset": "0x30"}, {"name": "PCR13", "offset": "0x34"}, {"name": "PCR14", "offset": "0x38"}, {"name": "PCR15", "offset": "0x3c"}, {"name": "PCR16", "offset": "0x40"}, {"name": "PCR17", "offset": "0x44"}, {"name": "PCR18", "offset": "0x48"}, {"name": "PCR19", "offset": "0x4c"}, {"name": "PCR20", "offset": "0x50"}, {"name": "PCR21", "offset": "0x54"}, {"name": "PCR22", "offset": "0x58"}, {"name": "PCR23", "offset": "0x5c"}, {"name": "PCR24", "offset": "0x60"}, {"name": "PCR25", "offset": "0x64"}, {"name": "PCR26", "offset": "0x68"}, {"name": "PCR27", "offset": "0x6c"}, {"name": "PCR28", "offset": "0x70"}, {"name": "PCR29", "offset": "0x74"}, {"name": "PCR30", "offset": "0x78"}, {"name": "PCR31", "offset": "0x7c"}, {"name": "GPCLR", "offset": "0x80"}, {"name": "GPCHR", "offset": "0x84"}, {"name": "ISFR", "offset": "0xa0"}, {"name": "DFER", "offset": "0xc0"}, {"name": "DFCR", "offset": "0xc4"}, {"name": "DFWR", "offset": "0xc8"}]}, {"name": "PORTB", "start": "0x4004a000", "end": "0x4004a0cb", "size": "0xcc", "comment": "", "registers": [{"name": "PCR0", "offset": "0x0"}, {"name": "PCR1", "offset": "0x4"}, {"name": "PCR2", "offset": "0x8"}, {"name": "PCR3", "offset": "0xc"}, {"name": "PCR4", "offset": "0x10"}, {"name": "PCR5", "offset": "0x14"}, {"name": "PCR6", "offset": "0x18"}, {"name": "PCR7", "offset": "0x1c"}, {"name": "PCR8", "offset": "0x20"}, {"name": "PCR9", "offset": "0x24"}, {"name": "PCR10", "offset": "0x28"}, {"name": "PCR11", "offset": "0x2c"}, {"name": "PCR12", "offset": "0x30"}, {"name": "PCR13", "offset": "0x34"}, {"name": "PCR14", "offset": "0x38"}, {"name": "PCR15", "offset": "0x3c"}, {"name": "PCR16", "offset": "0x40"}, {"name": "PCR17", "offset": "0x44"}, {"name": "PCR18", "offset": "0x48"}, {"name": "PCR19", "offset": "0x4c"}, {"name": "PCR20", "offset": "0x50"}, {"name": "PCR21", "offset": "0x54"}, {"name": "PCR22", "offset": "0x58"}, {"name": "PCR23", "offset": "0x5c"}, {"name": "PCR24", "offset": "0x60"}, {"name": "PCR25", "offset": "0x64"}, {"name": "PCR26", "offset": "0x68"}, {"name": "PCR27", "offset": "0x6c"}, {"name": "PCR28", "offset": "0x70"}, {"name": "PCR29", "offset": "0x74"}, {"name": "PCR30", "offset": "0x78"}, {"name": "PCR31", "offset": "0x7c"}, {"name": "GPCLR", "offset": "0x80"}, {"name": "GPCHR", "offset": "0x84"}, {"name": "ISFR", "offset": "0xa0"}, {"name": "DFER", "offset": "0xc0"}, {"name": "DFCR", "offset": "0xc4"}, {"name": "DFWR", "offset": "0xc8"}]}, {"name": "PORTC", "start": "0x4004b000", "end": "0x4004b0cb", "size": "0xcc", "comment": "", "registers": [{"name": "PCR0", "offset": "0x0"}, {"name": "PCR1", "offset": "0x4"}, {"name": "PCR2", "offset": "0x8"}, {"name": "PCR3", "offset": "0xc"}, {"name": "PCR4", "offset": "0x10"}, {"name": "PCR5", "offset": "0x14"}, {"name": "PCR6", "offset": "0x18"}, {"name": "PCR7", "offset": "0x1c"}, {"name": "PCR8", "offset": "0x20"}, {"name": "PCR9", "offset": "0x24"}, {"name": "PCR10", "offset": "0x28"}, {"name": "PCR11", "offset": "0x2c"}, {"name": "PCR12", "offset": "0x30"}, {"name": "PCR13", "offset": "0x34"}, {"name": "PCR14", "offset": "0x38"}, {"name": "PCR15", "offset": "0x3c"}, {"name": "PCR16", "offset": "0x40"}, {"name": "PCR17", "offset": "0x44"}, {"name": "PCR18", "offset": "0x48"}, {"name": "PCR19", "offset": "0x4c"}, {"name": "PCR20", "offset": "0x50"}, {"name": "PCR21", "offset": "0x54"}, {"name": "PCR22", "offset": "0x58"}, {"name": "PCR23", "offset": "0x5c"}, {"name": "PCR24", "offset": "0x60"}, {"name": "PCR25", "offset": "0x64"}, {"name": "PCR26", "offset": "0x68"}, {"name": "PCR27", "offset": "0x6c"}, {"name": "PCR28", "offset": "0x70"}, {"name": "PCR29", "offset": "0x74"}, {"name": "PCR30", "offset": "0x78"}, {"name": "PCR31", "offset": "0x7c"}, {"name": "GPCLR", "offset": "0x80"}, {"name": "GPCHR", "offset": "0x84"}, {"name": "ISFR", "offset": "0xa0"}, {"name": "DFER", "offset": "0xc0"}, {"name": "DFCR", "offset": "0xc4"}, {"name": "DFWR", "offset": "0xc8"}]}, {"name": "PORTD", "start": "0x4004c000", "end": "0x4004c0cb", "size": "0xcc", "comment": "", "registers": [{"name": "PCR0", "offset": "0x0"}, {"name": "PCR1", "offset": "0x4"}, {"name": "PCR2", "offset": "0x8"}, {"name": "PCR3", "offset": "0xc"}, {"name": "PCR4", "offset": "0x10"}, {"name": "PCR5", "offset": "0x14"}, {"name": "PCR6", "offset": "0x18"}, {"name": "PCR7", "offset": "0x1c"}, {"name": "PCR8", "offset": "0x20"}, {"name": "PCR9", "offset": "0x24"}, {"name": "PCR10", "offset": "0x28"}, {"name": "PCR11", "offset": "0x2c"}, {"name": "PCR12", "offset": "0x30"}, {"name": "PCR13", "offset": "0x34"}, {"name": "PCR14", "offset": "0x38"}, {"name": "PCR15", "offset": "0x3c"}, {"name": "PCR16", "offset": "0x40"}, {"name": "PCR17", "offset": "0x44"}, {"name": "PCR18", "offset": "0x48"}, {"name": "PCR19", "offset": "0x4c"}, {"name": "PCR20", "offset": "0x50"}, {"name": "PCR21", "offset": "0x54"}, {"name": "PCR22", "offset": "0x58"}, {"name": "PCR23", "offset": "0x5c"}, {"name": "PCR24", "offset": "0x60"}, {"name": "PCR25", "offset": "0x64"}, {"name": "PCR26", "offset": "0x68"}, {"name": "PCR27", "offset": "0x6c"}, {"name": "PCR28", "offset": "0x70"}, {"name": "PCR29", "offset": "0x74"}, {"name": "PCR30", "offset": "0x78"}, {"name": "PCR31", "offset": "0x7c"}, {"name": "GPCLR", "offset": "0x80"}, {"name": "GPCHR", "offset": "0x84"}, {"name": "ISFR", "offset": "0xa0"}, {"name": "DFER", "offset": "0xc0"}, {"name": "DFCR", "offset": "0xc4"}, {"name": "DFWR", "offset": "0xc8"}]}, {"name": "PORTE", "start": "0x4004d000", "end": "0x4004d0cb", "size": "0xcc", "comment": "", "registers": [{"name": "PCR0", "offset": "0x0"}, {"name": "PCR1", "offset": "0x4"}, {"name": "PCR2", "offset": "0x8"}, {"name": "PCR3", "offset": "0xc"}, {"name": "PCR4", "offset": "0x10"}, {"name": "PCR5", "offset": "0x14"}, {"name": "PCR6", "offset": "0x18"}, {"name": "PCR7", "offset": "0x1c"}, {"name": "PCR8", "offset": "0x20"}, {"name": "PCR9", "offset": "0x24"}, {"name": "PCR10", "offset": "0x28"}, {"name": "PCR11", "offset": "0x2c"}, {"name": "PCR12", "offset": "0x30"}, {"name": "PCR13", "offset": "0x34"}, {"name": "PCR14", "offset": "0x38"}, {"name": "PCR15", "offset": "0x3c"}, {"name": "PCR16", "offset": "0x40"}, {"name": "PCR17", "offset": "0x44"}, {"name": "PCR18", "offset": "0x48"}, {"name": "PCR19", "offset": "0x4c"}, {"name": "PCR20", "offset": "0x50"}, {"name": "PCR21", "offset": "0x54"}, {"name": "PCR22", "offset": "0x58"}, {"name": "PCR23", "offset": "0x5c"}, {"name": "PCR24", "offset": "0x60"}, {"name": "PCR25", "offset": "0x64"}, {"name": "PCR26", "offset": "0x68"}, {"name": "PCR27", "offset": "0x6c"}, {"name": "PCR28", "offset": "0x70"}, {"name": "PCR29", "offset": "0x74"}, {"name": "PCR30", "offset": "0x78"}, {"name": "PCR31", "offset": "0x7c"}, {"name": "GPCLR", "offset": "0x80"}, {"name": "GPCHR", "offset": "0x84"}, {"name": "ISFR", "offset": "0xa0"}, {"name": "DFER", "offset": "0xc0"}, {"name": "DFCR", "offset": "0xc4"}, {"name": "DFWR", "offset": "0xc8"}]}, {"name": "WDOG", "start": "0x40052000", "end": "0x40052017", "size": "0x18", "comment": "", "registers": [{"name": "STCTRLH", "offset": "0x0", "size": "0x10"}, {"name": "STCTRLL", "offset": "0x2", "size": "0x10"}, {"name": "TOVALH", "offset": "0x4", "size": "0x10"}, {"name": "TOVALL", "offset": "0x6", "size": "0x10"}, {"name": "WINH", "offset": "0x8", "size": "0x10"}, {"name": "WINL", "offset": "0xa", "size": "0x10"}, {"name": "REFRESH", "offset": "0xc", "size": "0x10"}, {"name": "UNLOCK", "offset": "0xe", "size": "0x10"}, {"name": "TMROUTH", "offset": "0x10", "size": "0x10"}, {"name": "TMROUTL", "offset": "0x12", "size": "0x10"}, {"name": "RSTCNT", "offset": "0x14", "size": "0x10"}, {"name": "PRESC", "offset": "0x16", "size": "0x10"}]}, {"name": "EWM", "start": "0x40061000", "end": "0x40061005", "size": "0x6", "comment": "", "registers": [{"name": "CTRL", "offset": "0x0", "size": "0x8"}, {"name": "SERV", "offset": "0x1", "size": "0x8"}, {"name": "CMPL", "offset": "0x2", "size": "0x8"}, {"name": "CMPH", "offset": "0x3", "size": "0x8"}, {"name": "CLKPRESCALER", "offset": "0x5", "size": "0x8"}]}, {"name": "CMT", "start": "0x40062000", "end": "0x4006200b", "size": "0xc", "comment": "", "registers": [{"name": "CGH1", "offset": "0x0", "size": "0x8"}, {"name": "CGL1", "offset": "0x1", "size": "0x8"}, {"name": "CGH2", "offset": "0x2", "size": "0x8"}, {"name": "CGL2", "offset": "0x3", "size": "0x8"}, {"name": "OC", "offset": "0x4", "size": "0x8"}, {"name": "MSC", "offset": "0x5", "size": "0x8"}, {"name": "CMD1", "offset": "0x6", "size": "0x8"}, {"name": "CMD2", "offset": "0x7", "size": "0x8"}, {"name": "CMD3", "offset": "0x8", "size": "0x8"}, {"name": "CMD4", "offset": "0x9", "size": "0x8"}, {"name": "PPS", "offset": "0xa", "size": "0x8"}, {"name": "DMA", "offset": "0xb", "size": "0x8"}]}, {"name": "MCG", "start": "0x40064000", "end": "0x4006400f", "size": "0x10", "comment": "", "registers": [{"name": "C1", "offset": "0x0", "size": "0x8"}, {"name": "C2", "offset": "0x1", "size": "0x8"}, {"name": "C3", "offset": "0x2", "size": "0x8"}, {"name": "C4", "offset": "0x3", "size": "0x8"}, {"name": "C5", "offset": "0x4", "size": "0x8"}, {"name": "C6", "offset": "0x5", "size": "0x8"}, {"name": "S", "offset": "0x6", "size": "0x8"}, {"name": "SC", "offset": "0x8", "size": "0x8"}, {"name": "ATCVH", "offset": "0xa", "size": "0x8"}, {"name": "ATCVL", "offset": "0xb", "size": "0x8"}, {"name": "C7", "offset": "0xc", "size": "0x8"}, {"name": "C8", "offset": "0xd", "size": "0x8"}, {"name": "C9", "offset": "0xe", "size": "0x8"}, {"name": "C10", "offset": "0xf", "size": "0x8"}]}, {"name": "OSC", "start": "0x40065000", "end": "0x40065000", "size": "0x1", "comment": "", "registers": [{"name": "CR", "offset": "0x0", "size": "0x8"}]}, {"name": "I2C0", "start": "0x40066000", "end": "0x4006600b", "size": "0xc", "comment": "", "registers": [{"name": "A1", "offset": "0x0", "size": "0x8"}, {"name": "F", "offset": "0x1", "size": "0x8"}, {"name": "C1", "offset": "0x2", "size": "0x8"}, {"name": "S", "offset": "0x3", "size": "0x8"}, {"name": "D", "offset": "0x4", "size": "0x8"}, {"name": "C2", "offset": "0x5", "size": "0x8"}, {"name": "FLT", "offset": "0x6", "size": "0x8"}, {"name": "RA", "offset": "0x7", "size": "0x8"}, {"name": "SMB", "offset": "0x8", "size": "0x8"}, {"name": "A2", "offset": "0x9", "size": "0x8"}, {"name": "SLTH", "offset": "0xa", "size": "0x8"}, {"name": "SLTL", "offset": "0xb", "size": "0x8"}]}, {"name": "I2C1", "start": "0x40067000", "end": "0x4006700b", "size": "0xc", "comment": "", "registers": [{"name": "A1", "offset": "0x0", "size": "0x8"}, {"name": "F", "offset": "0x1", "size": "0x8"}, {"name": "C1", "offset": "0x2", "size": "0x8"}, {"name": "S", "offset": "0x3", "size": "0x8"}, {"name": "D", "offset": "0x4", "size": "0x8"}, {"name": "C2", "offset": "0x5", "size": "0x8"}, {"name": "FLT", "offset": "0x6", "size": "0x8"}, {"name": "RA", "offset": "0x7", "size": "0x8"}, {"name": "SMB", "offset": "0x8", "size": "0x8"}, {"name": "A2", "offset": "0x9", "size": "0x8"}, {"name": "SLTH", "offset": "0xa", "size": "0x8"}, {"name": "SLTL", "offset": "0xb", "size": "0x8"}]}, {"name": "UART0", "start": "0x4006a000", "end": "0x4006a031", "size": "0x32", "comment": "", "registers": [{"name": "BDH", "offset": "0x0", "size": "0x8"}, {"name": "BDL", "offset": "0x1", "size": "0x8"}, {"name": "C1", "offset": "0x2", "size": "0x8"}, {"name": "C2", "offset": "0x3", "size": "0x8"}, {"name": "S1", "offset": "0x4", "size": "0x8"}, {"name": "S2", "offset": "0x5", "size": "0x8"}, {"name": "C3", "offset": "0x6", "size": "0x8"}, {"name": "D", "offset": "0x7", "size": "0x8"}, {"name": "MA1", "offset": "0x8", "size": "0x8"}, {"name": "MA2", "offset": "0x9", "size": "0x8"}, {"name": "C4", "offset": "0xa", "size": "0x8"}, {"name": "C5", "offset": "0xb", "size": "0x8"}, {"name": "ED", "offset": "0xc", "size": "0x8"}, {"name": "MODEM", "offset": "0xd", "size": "0x8"}, {"name": "IR", "offset": "0xe", "size": "0x8"}, {"name": "PFIFO", "offset": "0x10", "size": "0x8"}, {"name": "CFIFO", "offset": "0x11", "size": "0x8"}, {"name": "SFIFO", "offset": "0x12", "size": "0x8"}, {"name": "TWFIFO", "offset": "0x13", "size": "0x8"}, {"name": "TCFIFO", "offset": "0x14", "size": "0x8"}, {"name": "RWFIFO", "offset": "0x15", "size": "0x8"}, {"name": "RCFIFO", "offset": "0x16", "size": "0x8"}, {"name": "C7816", "offset": "0x18", "size": "0x8"}, {"name": "IE7816", "offset": "0x19", "size": "0x8"}, {"name": "IS7816", "offset": "0x1a", "size": "0x8"}, {"name": "WP7816T0", "offset": "0x1b", "size": "0x8"}, {"name": "WP7816T1", "offset": "0x1b", "size": "0x8"}, {"name": "WN7816", "offset": "0x1c", "size": "0x8"}, {"name": "WF7816", "offset": "0x1d", "size": "0x8"}, {"name": "ET7816", "offset": "0x1e", "size": "0x8"}, {"name": "TL7816", "offset": "0x1f", "size": "0x8"}, {"name": "C6", "offset": "0x21", "size": "0x8"}, {"name": "PCTH", "offset": "0x22", "size": "0x8"}, {"name": "PCTL", "offset": "0x23", "size": "0x8"}, {"name": "B1T", "offset": "0x24", "size": "0x8"}, {"name": "SDTH", "offset": "0x25", "size": "0x8"}, {"name": "SDTL", "offset": "0x26", "size": "0x8"}, {"name": "PRE", "offset": "0x27", "size": "0x8"}, {"name": "TPL", "offset": "0x28", "size": "0x8"}, {"name": "IE", "offset": "0x29", "size": "0x8"}, {"name": "WB", "offset": "0x2a", "size": "0x8"}, {"name": "S3", "offset": "0x2b", "size": "0x8"}, {"name": "S4", "offset": "0x2c", "size": "0x8"}, {"name": "RPL", "offset": "0x2d", "size": "0x8"}, {"name": "RPREL", "offset": "0x2e", "size": "0x8"}, {"name": "CPW", "offset": "0x2f", "size": "0x8"}, {"name": "RIDT", "offset": "0x30", "size": "0x8"}, {"name": "TIDT", "offset": "0x31", "size": "0x8"}]}, {"name": "UART1", "start": "0x4006b000", "end": "0x4006b016", "size": "0x17", "comment": "", "registers": [{"name": "BDH", "offset": "0x0", "size": "0x8"}, {"name": "BDL", "offset": "0x1", "size": "0x8"}, {"name": "C1", "offset": "0x2", "size": "0x8"}, {"name": "C2", "offset": "0x3", "size": "0x8"}, {"name": "S1", "offset": "0x4", "size": "0x8"}, {"name": "S2", "offset": "0x5", "size": "0x8"}, {"name": "C3", "offset": "0x6", "size": "0x8"}, {"name": "D", "offset": "0x7", "size": "0x8"}, {"name": "MA1", "offset": "0x8", "size": "0x8"}, {"name": "MA2", "offset": "0x9", "size": "0x8"}, {"name": "C4", "offset": "0xa", "size": "0x8"}, {"name": "C5", "offset": "0xb", "size": "0x8"}, {"name": "ED", "offset": "0xc", "size": "0x8"}, {"name": "MODEM", "offset": "0xd", "size": "0x8"}, {"name": "IR", "offset": "0xe", "size": "0x8"}, {"name": "PFIFO", "offset": "0x10", "size": "0x8"}, {"name": "CFIFO", "offset": "0x11", "size": "0x8"}, {"name": "SFIFO", "offset": "0x12", "size": "0x8"}, {"name": "TWFIFO", "offset": "0x13", "size": "0x8"}, {"name": "TCFIFO", "offset": "0x14", "size": "0x8"}, {"name": "RWFIFO", "offset": "0x15", "size": "0x8"}, {"name": "RCFIFO", "offset": "0x16", "size": "0x8"}]}, {"name": "UART2", "start": "0x4006c000", "end": "0x4006c016", "size": "0x17", "comment": "", "registers": [{"name": "BDH", "offset": "0x0", "size": "0x8"}, {"name": "BDL", "offset": "0x1", "size": "0x8"}, {"name": "C1", "offset": "0x2", "size": "0x8"}, {"name": "C2", "offset": "0x3", "size": "0x8"}, {"name": "S1", "offset": "0x4", "size": "0x8"}, {"name": "S2", "offset": "0x5", "size": "0x8"}, {"name": "C3", "offset": "0x6", "size": "0x8"}, {"name": "D", "offset": "0x7", "size": "0x8"}, {"name": "MA1", "offset": "0x8", "size": "0x8"}, {"name": "MA2", "offset": "0x9", "size": "0x8"}, {"name": "C4", "offset": "0xa", "size": "0x8"}, {"name": "C5", "offset": "0xb", "size": "0x8"}, {"name": "ED", "offset": "0xc", "size": "0x8"}, {"name": "MODEM", "offset": "0xd", "size": "0x8"}, {"name": "IR", "offset": "0xe", "size": "0x8"}, {"name": "PFIFO", "offset": "0x10", "size": "0x8"}, {"name": "CFIFO", "offset": "0x11", "size": "0x8"}, {"name": "SFIFO", "offset": "0x12", "size": "0x8"}, {"name": "TWFIFO", "offset": "0x13", "size": "0x8"}, {"name": "TCFIFO", "offset": "0x14", "size": "0x8"}, {"name": "RWFIFO", "offset": "0x15", "size": "0x8"}, {"name": "RCFIFO", "offset": "0x16", "size": "0x8"}]}, {"name": "UART3", "start": "0x4006d000", "end": "0x4006d016", "size": "0x17", "comment": "", "registers": [{"name": "BDH", "offset": "0x0", "size": "0x8"}, {"name": "BDL", "offset": "0x1", "size": "0x8"}, {"name": "C1", "offset": "0x2", "size": "0x8"}, {"name": "C2", "offset": "0x3", "size": "0x8"}, {"name": "S1", "offset": "0x4", "size": "0x8"}, {"name": "S2", "offset": "0x5", "size": "0x8"}, {"name": "C3", "offset": "0x6", "size": "0x8"}, {"name": "D", "offset": "0x7", "size": "0x8"}, {"name": "MA1", "offset": "0x8", "size": "0x8"}, {"name": "MA2", "offset": "0x9", "size": "0x8"}, {"name": "C4", "offset": "0xa", "size": "0x8"}, {"name": "C5", "offset": "0xb", "size": "0x8"}, {"name": "ED", "offset": "0xc", "size": "0x8"}, {"name": "MODEM", "offset": "0xd", "size": "0x8"}, {"name": "IR", "offset": "0xe", "size": "0x8"}, {"name": "PFIFO", "offset": "0x10", "size": "0x8"}, {"name": "CFIFO", "offset": "0x11", "size": "0x8"}, {"name": "SFIFO", "offset": "0x12", "size": "0x8"}, {"name": "TWFIFO", "offset": "0x13", "size": "0x8"}, {"name": "TCFIFO", "offset": "0x14", "size": "0x8"}, {"name": "RWFIFO", "offset": "0x15", "size": "0x8"}, {"name": "RCFIFO", "offset": "0x16", "size": "0x8"}]}, {"name": "UART4", "start": "0x400ea000", "end": "0x400ea016", "size": "0x17", "comment": "", "registers": [{"name": "BDH", "offset": "0x0", "size": "0x8"}, {"name": "BDL", "offset": "0x1", "size": "0x8"}, {"name": "C1", "offset": "0x2", "size": "0x8"}, {"name": "C2", "offset": "0x3", "size": "0x8"}, {"name": "S1", "offset": "0x4", "size": "0x8"}, {"name": "S2", "offset": "0x5", "size": "0x8"}, {"name": "C3", "offset": "0x6", "size": "0x8"}, {"name": "D", "offset": "0x7", "size": "0x8"}, {"name": "MA1", "offset": "0x8", "size": "0x8"}, {"name": "MA2", "offset": "0x9", "size": "0x8"}, {"name": "C4", "offset": "0xa", "size": "0x8"}, {"name": "C5", "offset": "0xb", "size": "0x8"}, {"name": "ED", "offset": "0xc", "size": "0x8"}, {"name": "MODEM", "offset": "0xd", "size": "0x8"}, {"name": "IR", "offset": "0xe", "size": "0x8"}, {"name": "PFIFO", "offset": "0x10", "size": "0x8"}, {"name": "CFIFO", "offset": "0x11", "size": "0x8"}, {"name": "SFIFO", "offset": "0x12", "size": "0x8"}, {"name": "TWFIFO", "offset": "0x13", "size": "0x8"}, {"name": "TCFIFO", "offset": "0x14", "size": "0x8"}, {"name": "RWFIFO", "offset": "0x15", "size": "0x8"}, {"name": "RCFIFO", "offset": "0x16", "size": "0x8"}]}, {"name": "UART5", "start": "0x400eb000", "end": "0x400eb016", "size": "0x17", "comment": "", "registers": [{"name": "BDH", "offset": "0x0", "size": "0x8"}, {"name": "BDL", "offset": "0x1", "size": "0x8"}, {"name": "C1", "offset": "0x2", "size": "0x8"}, {"name": "C2", "offset": "0x3", "size": "0x8"}, {"name": "S1", "offset": "0x4", "size": "0x8"}, {"name": "S2", "offset": "0x5", "size": "0x8"}, {"name": "C3", "offset": "0x6", "size": "0x8"}, {"name": "D", "offset": "0x7", "size": "0x8"}, {"name": "MA1", "offset": "0x8", "size": "0x8"}, {"name": "MA2", "offset": "0x9", "size": "0x8"}, {"name": "C4", "offset": "0xa", "size": "0x8"}, {"name": "C5", "offset": "0xb", "size": "0x8"}, {"name": "ED", "offset": "0xc", "size": "0x8"}, {"name": "MODEM", "offset": "0xd", "size": "0x8"}, {"name": "IR", "offset": "0xe", "size": "0x8"}, {"name": "PFIFO", "offset": "0x10", "size": "0x8"}, {"name": "CFIFO", "offset": "0x11", "size": "0x8"}, {"name": "SFIFO", "offset": "0x12", "size": "0x8"}, {"name": "TWFIFO", "offset": "0x13", "size": "0x8"}, {"name": "TCFIFO", "offset": "0x14", "size": "0x8"}, {"name": "RWFIFO", "offset": "0x15", "size": "0x8"}, {"name": "RCFIFO", "offset": "0x16", "size": "0x8"}]}, {"name": "USB0", "start": "0x40072000", "end": "0x40072114", "size": "0x115", "comment": "", "registers": [{"name": "PERID", "offset": "0x0", "size": "0x8"}, {"name": "IDCOMP", "offset": "0x4", "size": "0x8"}, {"name": "REV", "offset": "0x8", "size": "0x8"}, {"name": "ADDINFO", "offset": "0xc", "size": "0x8"}, {"name": "OTGISTAT", "offset": "0x10", "size": "0x8"}, {"name": "OTGICR", "offset": "0x14", "size": "0x8"}, {"name": "OTGSTAT", "offset": "0x18", "size": "0x8"}, {"name": "OTGCTL", "offset": "0x1c", "size": "0x8"}, {"name": "ISTAT", "offset": "0x80", "size": "0x8"}, {"name": "INTEN", "offset": "0x84", "size": "0x8"}, {"name": "ERRSTAT", "offset": "0x88", "size": "0x8"}, {"name": "ERREN", "offset": "0x8c", "size": "0x8"}, {"name": "STAT", "offset": "0x90", "size": "0x8"}, {"name": "CTL", "offset": "0x94", "size": "0x8"}, {"name": "ADDR", "offset": "0x98", "size": "0x8"}, {"name": "BDTPAGE1", "offset": "0x9c", "size": "0x8"}, {"name": "FRMNUML", "offset": "0xa0", "size": "0x8"}, {"name": "FRMNUMH", "offset": "0xa4", "size": "0x8"}, {"name": "TOKEN", "offset": "0xa8", "size": "0x8"}, {"name": "SOFTHLD", "offset": "0xac", "size": "0x8"}, {"name": "BDTPAGE2", "offset": "0xb0", "size": "0x8"}, {"name": "BDTPAGE3", "offset": "0xb4", "size": "0x8"}, {"name": "USBCTRL", "offset": "0x100", "size": "0x8"}, {"name": "OBSERVE", "offset": "0x104", "size": "0x8"}, {"name": "CONTROL", "offset": "0x108", "size": "0x8"}, {"name": "USBTRC0", "offset": "0x10c", "size": "0x8"}, {"name": "USBFRMADJUST", "offset": "0x114", "size": "0x8"}, {"name": "ENDPT0", "offset": "0xc0", "size": "0x8"}, {"name": "ENDPT1", "offset": "0xc4", "size": "0x8"}, {"name": "ENDPT2", "offset": "0xc8", "size": "0x8"}, {"name": "ENDPT3", "offset": "0xcc", "size": "0x8"}, {"name": "ENDPT4", "offset": "0xd0", "size": "0x8"}, {"name": "ENDPT5", "offset": "0xd4", "size": "0x8"}, {"name": "ENDPT6", "offset": "0xd8", "size": "0x8"}, {"name": "ENDPT7", "offset": "0xdc", "size": "0x8"}, {"name": "ENDPT8", "offset": "0xe0", "size": "0x8"}, {"name": "ENDPT9", "offset": "0xe4", "size": "0x8"}, {"name": "ENDPT10", "offset": "0xe8", "size": "0x8"}, {"name": "ENDPT11", "offset": "0xec", "size": "0x8"}, {"name": "ENDPT12", "offset": "0xf0", "size": "0x8"}, {"name": "ENDPT13", "offset": "0xf4", "size": "0x8"}, {"name": "ENDPT14", "offset": "0xf8", "size": "0x8"}, {"name": "ENDPT15", "offset": "0xfc", "size": "0x8"}]}, {"name": "CMP0", "start": "0x40073000", "end": "0x40073005", "size": "0x6", "comment": "", "registers": [{"name": "CR0", "offset": "0x0", "size": "0x8"}, {"name": "CR1", "offset": "0x1", "size": "0x8"}, {"name": "FPR", "offset": "0x2", "size": "0x8"}, {"name": "SCR", "offset": "0x3", "size": "0x8"}, {"name": "DACCR", "offset": "0x4", "size": "0x8"}, {"name": "MUXCR", "offset": "0x5", "size": "0x8"}]}, {"name": "CMP1", "start": "0x40073008", "end": "0x4007300d", "size": "0x6", "comment": "", "registers": [{"name": "CR0", "offset": "0x0", "size": "0x8"}, {"name": "CR1", "offset": "0x1", "size": "0x8"}, {"name": "FPR", "offset": "0x2", "size": "0x8"}, {"name": "SCR", "offset": "0x3", "size": "0x8"}, {"name": "DACCR", "offset": "0x4", "size": "0x8"}, {"name": "MUXCR", "offset": "0x5", "size": "0x8"}]}, {"name": "CMP2", "start": "0x40073010", "end": "0x40073015", "size": "0x6", "comment": "", "registers": [{"name": "CR0", "offset": "0x0", "size": "0x8"}, {"name": "CR1", "offset": "0x1", "size": "0x8"}, {"name": "FPR", "offset": "0x2", "size": "0x8"}, {"name": "SCR", "offset": "0x3", "size": "0x8"}, {"name": "DACCR", "offset": "0x4", "size": "0x8"}, {"name": "MUXCR", "offset": "0x5", "size": "0x8"}]}, {"name": "VREF", "start": "0x40074000", "end": "0x40074001", "size": "0x2", "comment": "", "registers": [{"name": "TRM", "offset": "0x0", "size": "0x8"}, {"name": "SC", "offset": "0x1", "size": "0x8"}]}, {"name": "LLWU", "start": "0x4007c000", "end": "0x4007c00a", "size": "0xb", "comment": "", "registers": [{"name": "PE1", "offset": "0x0", "size": "0x8"}, {"name": "PE2", "offset": "0x1", "size": "0x8"}, {"name": "PE3", "offset": "0x2", "size": "0x8"}, {"name": "PE4", "offset": "0x3", "size": "0x8"}, {"name": "ME", "offset": "0x4", "size": "0x8"}, {"name": "F1", "offset": "0x5", "size": "0x8"}, {"name": "F2", "offset": "0x6", "size": "0x8"}, {"name": "F3", "offset": "0x7", "size": "0x8"}, {"name": "FILT1", "offset": "0x8", "size": "0x8"}, {"name": "FILT2", "offset": "0x9", "size": "0x8"}, {"name": "RST", "offset": "0xa", "size": "0x8"}]}, {"name": "PMC", "start": "0x4007d000", "end": "0x4007d002", "size": "0x3", "comment": "", "registers": [{"name": "LVDSC1", "offset": "0x0", "size": "0x8"}, {"name": "LVDSC2", "offset": "0x1", "size": "0x8"}, {"name": "REGSC", "offset": "0x2", "size": "0x8"}]}, {"name": "SMC", "start": "0x4007e000", "end": "0x4007e003", "size": "0x4", "comment": "", "registers": [{"name": "PMPROT", "offset": "0x0", "size": "0x8"}, {"name": "PMCTRL", "offset": "0x1", "size": "0x8"}, {"name": "VLLSCTRL", "offset": "0x2", "size": "0x8"}, {"name": "PMSTAT", "offset": "0x3", "size": "0x8"}]}, {"name": "RCM", "start": "0x4007f000", "end": "0x4007f007", "size": "0x8", "comment": "", "registers": [{"name": "SRS0", "offset": "0x0", "size": "0x8"}, {"name": "SRS1", "offset": "0x1", "size": "0x8"}, {"name": "RPFC", "offset": "0x4", "size": "0x8"}, {"name": "RPFW", "offset": "0x5", "size": "0x8"}, {"name": "MR", "offset": "0x7", "size": "0x8"}]}, {"name": "RNG", "start": "0x400a0000", "end": "0x400a000f", "size": "0x10", "comment": "", "registers": [{"name": "CR", "offset": "0x0"}, {"name": "SR", "offset": "0x4"}, {"name": "ER", "offset": "0x8"}, {"name": "OR", "offset": "0xc"}]}, {"name": "SDHC", "start": "0x400b1000", "end": "0x400b10ff", "size": "0x100", "comment": "", "registers": [{"name": "DSADDR", "offset": "0x0"}, {"name": "BLKATTR", "offset": "0x4"}, {"name": "CMDARG", "offset": "0x8"}, {"name": "XFERTYP", "offset": "0xc"}, {"name": "CMDRSP0", "offset": "0x10"}, {"name": "CMDRSP1", "offset": "0x14"}, {"name": "CMDRSP2", "offset": "0x18"}, {"name": "CMDRSP3", "offset": "0x1c"}, {"name": "DATPORT", "offset": "0x20"}, {"name": "PRSSTAT", "offset": "0x24"}, {"name": "PROCTL", "offset": "0x28"}, {"name": "SYSCTL", "offset": "0x2c"}, {"name": "IRQSTAT", "offset": "0x30"}, {"name": "IRQSTATEN", "offset": "0x34"}, {"name": "IRQSIGEN", "offset": "0x38"}, {"name": "AC12ERR", "offset": "0x3c"}, {"name": "HTCAPBLT", "offset": "0x40"}, {"name": "WML", "offset": "0x44"}, {"name": "FEVT", "offset": "0x50"}, {"name": "ADMAES", "offset": "0x54"}, {"name": "ADSADDR", "offset": "0x58"}, {"name": "VENDOR", "offset": "0xc0"}, {"name": "MMCBOOT", "offset": "0xc4"}, {"name": "HOSTVER", "offset": "0xfc"}]}, {"name": "ENET", "start": "0x400c0000", "end": "0x400c0623", "size": "0x624", "comment": "", "registers": [{"name": "EIR", "offset": "0x4"}, {"name": "EIMR", "offset": "0x8"}, {"name": "RDAR", "offset": "0x10"}, {"name": "TDAR", "offset": "0x14"}, {"name": "ECR", "offset": "0x24"}, {"name": "MMFR", "offset": "0x40"}, {"name": "MSCR", "offset": "0x44"}, {"name": "MIBC", "offset": "0x64"}, {"name": "RCR", "offset": "0x84"}, {"name": "TCR", "offset": "0xc4"}, {"name": "PALR", "offset": "0xe4"}, {"name": "PAUR", "offset": "0xe8"}, {"name": "OPD", "offset": "0xec"}, {"name": "IAUR", "offset": "0x118"}, {"name": "IALR", "offset": "0x11c"}, {"name": "GAUR", "offset": "0x120"}, {"name": "GALR", "offset": "0x124"}, {"name": "TFWR", "offset": "0x144"}, {"name": "RDSR", "offset": "0x180"}, {"name": "TDSR", "offset": "0x184"}, {"name": "MRBR", "offset": "0x188"}, {"name": "RSFL", "offset": "0x190"}, {"name": "RSEM", "offset": "0x194"}, {"name": "RAEM", "offset": "0x198"}, {"name": "RAFL", "offset": "0x19c"}, {"name": "TSEM", "offset": "0x1a0"}, {"name": "TAEM", "offset": "0x1a4"}, {"name": "TAFL", "offset": "0x1a8"}, {"name": "TIPG", "offset": "0x1ac"}, {"name": "FTRL", "offset": "0x1b0"}, {"name": "TACC", "offset": "0x1c0"}, {"name": "RACC", "offset": "0x1c4"}, {"name": "RMON_T_DROP", "offset": "0x200"}, {"name": "RMON_T_PACKETS", "offset": "0x204"}, {"name": "RMON_T_BC_PKT", "offset": "0x208"}, {"name": "RMON_T_MC_PKT", "offset": "0x20c"}, {"name": "RMON_T_CRC_ALIGN", "offset": "0x210"}, {"name": "RMON_T_UNDERSIZE", "offset": "0x214"}, {"name": "RMON_T_OVERSIZE", "offset": "0x218"}, {"name": "RMON_T_FRAG", "offset": "0x21c"}, {"name": "RMON_T_JAB", "offset": "0x220"}, {"name": "RMON_T_COL", "offset": "0x224"}, {"name": "RMON_T_P64", "offset": "0x228"}, {"name": "RMON_T_P65TO127", "offset": "0x22c"}, {"name": "RMON_T_P128TO255", "offset": "0x230"}, {"name": "RMON_T_P256TO511", "offset": "0x234"}, {"name": "RMON_T_P512TO1023", "offset": "0x238"}, {"name": "RMON_T_P1024TO2047", "offset": "0x23c"}, {"name": "RMON_T_P_GTE2048", "offset": "0x240"}, {"name": "RMON_T_OCTETS", "offset": "0x244"}, {"name": "IEEE_T_DROP", "offset": "0x248"}, {"name": "IEEE_T_FRAME_OK", "offset": "0x24c"}, {"name": "IEEE_T_1COL", "offset": "0x250"}, {"name": "IEEE_T_MCOL", "offset": "0x254"}, {"name": "IEEE_T_DEF", "offset": "0x258"}, {"name": "IEEE_T_LCOL", "offset": "0x25c"}, {"name": "IEEE_T_EXCOL", "offset": "0x260"}, {"name": "IEEE_T_MACERR", "offset": "0x264"}, {"name": "IEEE_T_CSERR", "offset": "0x268"}, {"name": "IEEE_T_SQE", "offset": "0x26c"}, {"name": "IEEE_T_FDXFC", "offset": "0x270"}, {"name": "IEEE_T_OCTETS_OK", "offset": "0x274"}, {"name": "RMON_R_PACKETS", "offset": "0x284"}, {"name": "RMON_R_BC_PKT", "offset": "0x288"}, {"name": "RMON_R_MC_PKT", "offset": "0x28c"}, {"name": "RMON_R_CRC_ALIGN", "offset": "0x290"}, {"name": "RMON_R_UNDERSIZE", "offset": "0x294"}, {"name": "RMON_R_OVERSIZE", "offset": "0x298"}, {"name": "RMON_R_FRAG", "offset": "0x29c"}, {"name": "RMON_R_JAB", "offset": "0x2a0"}, {"name": "RMON_R_RESVD_0", "offset": "0x2a4"}, {"name": "RMON_R_P64", "offset": "0x2a8"}, {"name": "RMON_R_P65TO127", "offset": "0x2ac"}, {"name": "RMON_R_P128TO255", "offset": "0x2b0"}, {"name": "RMON_R_P256TO511", "offset": "0x2b4"}, {"name": "RMON_R_P512TO1023", "offset": "0x2b8"}, {"name": "RMON_R_P1024TO2047", "offset": "0x2bc"}, {"name": "RMON_R_P_GTE2048", "offset": "0x2c0"}, {"name": "RMON_R_OCTETS", "offset": "0x2c4"}, {"name": "IEEE_R_DROP", "offset": "0x2c8"}, {"name": "IEEE_R_FRAME_OK", "offset": "0x2cc"}, {"name": "IEEE_R_CRC", "offset": "0x2d0"}, {"name": "IEEE_R_ALIGN", "offset": "0x2d4"}, {"name": "IEEE_R_MACERR", "offset": "0x2d8"}, {"name": "IEEE_R_FDXFC", "offset": "0x2dc"}, {"name": "IEEE_R_OCTETS_OK", "offset": "0x2e0"}, {"name": "ATCR", "offset": "0x400"}, {"name": "ATVR", "offset": "0x404"}, {"name": "ATOFF", "offset": "0x408"}, {"name": "ATPER", "offset": "0x40c"}, {"name": "ATCOR", "offset": "0x410"}, {"name": "ATINC", "offset": "0x414"}, {"name": "ATSTMP", "offset": "0x418"}, {"name": "TGSR", "offset": "0x604"}, {"name": "TCSR0", "offset": "0x608"}, {"name": "TCSR1", "offset": "0x610"}, {"name": "TCSR2", "offset": "0x618"}, {"name": "TCSR3", "offset": "0x620"}, {"name": "TCCR0", "offset": "0x60c"}, {"name": "TCCR1", "offset": "0x614"}, {"name": "TCCR2", "offset": "0x61c"}, {"name": "TCCR3", "offset": "0x624"}]}, {"name": "DAC0", "start": "0x400cc000", "end": "0x400cc023", "size": "0x24", "comment": "", "registers": [{"name": "SR", "offset": "0x20", "size": "0x8"}, {"name": "C0", "offset": "0x21", "size": "0x8"}, {"name": "C1", "offset": "0x22", "size": "0x8"}, {"name": "C2", "offset": "0x23", "size": "0x8"}, {"name": "DAT0L", "offset": "0x0", "size": "0x8"}, {"name": "DAT1L", "offset": "0x2", "size": "0x8"}, {"name": "DAT2L", "offset": "0x4", "size": "0x8"}, {"name": "DAT3L", "offset": "0x6", "size": "0x8"}, {"name": "DAT4L", "offset": "0x8", "size": "0x8"}, {"name": "DAT5L", "offset": "0xa", "size": "0x8"}, {"name": "DAT6L", "offset": "0xc", "size": "0x8"}, {"name": "DAT7L", "offset": "0xe", "size": "0x8"}, {"name": "DAT8L", "offset": "0x10", "size": "0x8"}, {"name": "DAT9L", "offset": "0x12", "size": "0x8"}, {"name": "DAT10L", "offset": "0x14", "size": "0x8"}, {"name": "DAT11L", "offset": "0x16", "size": "0x8"}, {"name": "DAT12L", "offset": "0x18", "size": "0x8"}, {"name": "DAT13L", "offset": "0x1a", "size": "0x8"}, {"name": "DAT14L", "offset": "0x1c", "size": "0x8"}, {"name": "DAT15L", "offset": "0x1e", "size": "0x8"}, {"name": "DAT0H", "offset": "0x1", "size": "0x8"}, {"name": "DAT1H", "offset": "0x3", "size": "0x8"}, {"name": "DAT2H", "offset": "0x5", "size": "0x8"}, {"name": "DAT3H", "offset": "0x7", "size": "0x8"}, {"name": "DAT4H", "offset": "0x9", "size": "0x8"}, {"name": "DAT5H", "offset": "0xb", "size": "0x8"}, {"name": "DAT6H", "offset": "0xd", "size": "0x8"}, {"name": "DAT7H", "offset": "0xf", "size": "0x8"}, {"name": "DAT8H", "offset": "0x11", "size": "0x8"}, {"name": "DAT9H", "offset": "0x13", "size": "0x8"}, {"name": "DAT10H", "offset": "0x15", "size": "0x8"}, {"name": "DAT11H", "offset": "0x17", "size": "0x8"}, {"name": "DAT12H", "offset": "0x19", "size": "0x8"}, {"name": "DAT13H", "offset": "0x1b", "size": "0x8"}, {"name": "DAT14H", "offset": "0x1d", "size": "0x8"}, {"name": "DAT15H", "offset": "0x1f", "size": "0x8"}]}, {"name": "DAC1", "start": "0x400cd000", "end": "0x400cd023", "size": "0x24", "comment": "", "registers": [{"name": "SR", "offset": "0x20", "size": "0x8"}, {"name": "C0", "offset": "0x21", "size": "0x8"}, {"name": "C1", "offset": "0x22", "size": "0x8"}, {"name": "C2", "offset": "0x23", "size": "0x8"}, {"name": "DAT0L", "offset": "0x0", "size": "0x8"}, {"name": "DAT1L", "offset": "0x2", "size": "0x8"}, {"name": "DAT2L", "offset": "0x4", "size": "0x8"}, {"name": "DAT3L", "offset": "0x6", "size": "0x8"}, {"name": "DAT4L", "offset": "0x8", "size": "0x8"}, {"name": "DAT5L", "offset": "0xa", "size": "0x8"}, {"name": "DAT6L", "offset": "0xc", "size": "0x8"}, {"name": "DAT7L", "offset": "0xe", "size": "0x8"}, {"name": "DAT8L", "offset": "0x10", "size": "0x8"}, {"name": "DAT9L", "offset": "0x12", "size": "0x8"}, {"name": "DAT10L", "offset": "0x14", "size": "0x8"}, {"name": "DAT11L", "offset": "0x16", "size": "0x8"}, {"name": "DAT12L", "offset": "0x18", "size": "0x8"}, {"name": "DAT13L", "offset": "0x1a", "size": "0x8"}, {"name": "DAT14L", "offset": "0x1c", "size": "0x8"}, {"name": "DAT15L", "offset": "0x1e", "size": "0x8"}, {"name": "DAT0H", "offset": "0x1", "size": "0x8"}, {"name": "DAT1H", "offset": "0x3", "size": "0x8"}, {"name": "DAT2H", "offset": "0x5", "size": "0x8"}, {"name": "DAT3H", "offset": "0x7", "size": "0x8"}, {"name": "DAT4H", "offset": "0x9", "size": "0x8"}, {"name": "DAT5H", "offset": "0xb", "size": "0x8"}, {"name": "DAT6H", "offset": "0xd", "size": "0x8"}, {"name": "DAT7H", "offset": "0xf", "size": "0x8"}, {"name": "DAT8H", "offset": "0x11", "size": "0x8"}, {"name": "DAT9H", "offset": "0x13", "size": "0x8"}, {"name": "DAT10H", "offset": "0x15", "size": "0x8"}, {"name": "DAT11H", "offset": "0x17", "size": "0x8"}, {"name": "DAT12H", "offset": "0x19", "size": "0x8"}, {"name": "DAT13H", "offset": "0x1b", "size": "0x8"}, {"name": "DAT14H", "offset": "0x1d", "size": "0x8"}, {"name": "DAT15H", "offset": "0x1f", "size": "0x8"}]}, {"name": "OPAMP0", "start": "0x400f5000", "end": "0x400f5002", "size": "0x3", "comment": "", "registers": [{"name": "C0", "offset": "0x0", "size": "0x8"}, {"name": "C1", "offset": "0x1", "size": "0x8"}, {"name": "C2", "offset": "0x2", "size": "0x8"}]}, {"name": "OPAMP1", "start": "0x400f5800", "end": "0x400f5802", "size": "0x3", "comment": "", "registers": [{"name": "C0", "offset": "0x0", "size": "0x8"}, {"name": "C1", "offset": "0x1", "size": "0x8"}, {"name": "C2", "offset": "0x2", "size": "0x8"}]}, {"name": "TRIAMP0", "start": "0x400f8000", "end": "0x400f8000", "size": "0x1", "comment": "", "registers": [{"name": "C0", "offset": "0x0", "size": "0x8"}]}, {"name": "TRIAMP1", "start": "0x400f8800", "end": "0x400f8800", "size": "0x1", "comment": "", "registers": [{"name": "C0", "offset": "0x0", "size": "0x8"}]}, {"name": "GPIOA", "start": "0x400ff000", "end": "0x400ff017", "size": "0x18", "comment": "", "registers": [{"name": "PDOR", "offset": "0x0"}, {"name": "PSOR", "offset": "0x4"}, {"name": "PCOR", "offset": "0x8"}, {"name": "PTOR", "offset": "0xc"}, {"name": "PDIR", "offset": "0x10"}, {"name": "PDDR", "offset": "0x14"}]}, {"name": "GPIOB", "start": "0x400ff040", "end": "0x400ff057", "size": "0x18", "comment": "", "registers": [{"name": "PDOR", "offset": "0x0"}, {"name": "PSOR", "offset": "0x4"}, {"name": "PCOR", "offset": "0x8"}, {"name": "PTOR", "offset": "0xc"}, {"name": "PDIR", "offset": "0x10"}, {"name": "PDDR", "offset": "0x14"}]}, {"name": "GPIOC", "start": "0x400ff080", "end": "0x400ff097", "size": "0x18", "comment": "", "registers": [{"name": "PDOR", "offset": "0x0"}, {"name": "PSOR", "offset": "0x4"}, {"name": "PCOR", "offset": "0x8"}, {"name": "PTOR", "offset": "0xc"}, {"name": "PDIR", "offset": "0x10"}, {"name": "PDDR", "offset": "0x14"}]}, {"name": "GPIOD", "start": "0x400ff0c0", "end": "0x400ff0d7", "size": "0x18", "comment": "", "registers": [{"name": "PDOR", "offset": "0x0"}, {"name": "PSOR", "offset": "0x4"}, {"name": "PCOR", "offset": "0x8"}, {"name": "PTOR", "offset": "0xc"}, {"name": "PDIR", "offset": "0x10"}, {"name": "PDDR", "offset": "0x14"}]}, {"name": "GPIOE", "start": "0x400ff100", "end": "0x400ff117", "size": "0x18", "comment": "", "registers": [{"name": "PDOR", "offset": "0x0"}, {"name": "PSOR", "offset": "0x4"}, {"name": "PCOR", "offset": "0x8"}, {"name": "PTOR", "offset": "0xc"}, {"name": "PDIR", "offset": "0x10"}, {"name": "PDDR", "offset": "0x14"}]}, {"name": "MCM", "start": "0xe0080000", "end": "0xe008002b", "size": "0x2c", "comment": "", "registers": [{"name": "PLASC", "offset": "0x8", "size": "0x10"}, {"name": "PLAMC", "offset": "0xa", "size": "0x10"}, {"name": "CR", "offset": "0xc"}, {"name": "ISR", "offset": "0x10"}, {"name": "ETBCC", "offset": "0x14"}, {"name": "ETBRL", "offset": "0x18"}, {"name": "ETBCNT", "offset": "0x1c"}, {"name": "PID", "offset": "0x30"}]}, {"name": "CAU", "start": "0xe0081000", "end": "0xe0081b6b", "size": "0xb6c", "comment": "", "registers": [{"name": "CAU_DIRECT0", "offset": "0x0"}, {"name": "CAU_DIRECT1", "offset": "0x4"}, {"name": "CAU_DIRECT2", "offset": "0x8"}, {"name": "CAU_DIRECT3", "offset": "0xc"}, {"name": "CAU_DIRECT4", "offset": "0x10"}, {"name": "CAU_DIRECT5", "offset": "0x14"}, {"name": "CAU_DIRECT6", "offset": "0x18"}, {"name": "CAU_DIRECT7", "offset": "0x1c"}, {"name": "CAU_DIRECT8", "offset": "0x20"}, {"name": "CAU_DIRECT9", "offset": "0x24"}, {"name": "CAU_DIRECT10", "offset": "0x28"}, {"name": "CAU_DIRECT11", "offset": "0x2c"}, {"name": "CAU_DIRECT12", "offset": "0x30"}, {"name": "CAU_DIRECT13", "offset": "0x34"}, {"name": "CAU_DIRECT14", "offset": "0x38"}, {"name": "CAU_DIRECT15", "offset": "0x3c"}, {"name": "CAU_LDR_CASR", "offset": "0x840"}, {"name": "CAU_LDR_CAA", "offset": "0x844"}, {"name": "CAU_LDR_CA0", "offset": "0x848"}, {"name": "CAU_LDR_CA1", "offset": "0x84c"}, {"name": "CAU_LDR_CA2", "offset": "0x850"}, {"name": "CAU_LDR_CA3", "offset": "0x854"}, {"name": "CAU_LDR_CA4", "offset": "0x858"}, {"name": "CAU_LDR_CA5", "offset": "0x85c"}, {"name": "CAU_LDR_CA6", "offset": "0x860"}, {"name": "CAU_LDR_CA7", "offset": "0x864"}, {"name": "CAU_LDR_CA8", "offset": "0x868"}, {"name": "CAU_STR_CASR", "offset": "0x880"}, {"name": "CAU_STR_CAA", "offset": "0x884"}, {"name": "CAU_STR_CA0", "offset": "0x888"}, {"name": "CAU_STR_CA1", "offset": "0x88c"}, {"name": "CAU_STR_CA2", "offset": "0x890"}, {"name": "CAU_STR_CA3", "offset": "0x894"}, {"name": "CAU_STR_CA4", "offset": "0x898"}, {"name": "CAU_STR_CA5", "offset": "0x89c"}, {"name": "CAU_STR_CA6", "offset": "0x8a0"}, {"name": "CAU_STR_CA7", "offset": "0x8a4"}, {"name": "CAU_STR_CA8", "offset": "0x8a8"}, {"name": "CAU_ADR_CASR", "offset": "0x8c0"}, {"name": "CAU_ADR_CAA", "offset": "0x8c4"}, {"name": "CAU_ADR_CA0", "offset": "0x8c8"}, {"name": "CAU_ADR_CA1", "offset": "0x8cc"}, {"name": "CAU_ADR_CA2", "offset": "0x8d0"}, {"name": "CAU_ADR_CA3", "offset": "0x8d4"}, {"name": "CAU_ADR_CA4", "offset": "0x8d8"}, {"name": "CAU_ADR_CA5", "offset": "0x8dc"}, {"name": "CAU_ADR_CA6", "offset": "0x8e0"}, {"name": "CAU_ADR_CA7", "offset": "0x8e4"}, {"name": "CAU_ADR_CA8", "offset": "0x8e8"}, {"name": "CAU_RADR_CASR", "offset": "0x900"}, {"name": "CAU_RADR_CAA", "offset": "0x904"}, {"name": "CAU_RADR_CA0", "offset": "0x908"}, {"name": "CAU_RADR_CA1", "offset": "0x90c"}, {"name": "CAU_RADR_CA2", "offset": "0x910"}, {"name": "CAU_RADR_CA3", "offset": "0x914"}, {"name": "CAU_RADR_CA4", "offset": "0x918"}, {"name": "CAU_RADR_CA5", "offset": "0x91c"}, {"name": "CAU_RADR_CA6", "offset": "0x920"}, {"name": "CAU_RADR_CA7", "offset": "0x924"}, {"name": "CAU_RADR_CA8", "offset": "0x928"}, {"name": "CAU_XOR_CASR", "offset": "0x980"}, {"name": "CAU_XOR_CAA", "offset": "0x984"}, {"name": "CAU_XOR_CA0", "offset": "0x988"}, {"name": "CAU_XOR_CA1", "offset": "0x98c"}, {"name": "CAU_XOR_CA2", "offset": "0x990"}, {"name": "CAU_XOR_CA3", "offset": "0x994"}, {"name": "CAU_XOR_CA4", "offset": "0x998"}, {"name": "CAU_XOR_CA5", "offset": "0x99c"}, {"name": "CAU_XOR_CA6", "offset": "0x9a0"}, {"name": "CAU_XOR_CA7", "offset": "0x9a4"}, {"name": "CAU_XOR_CA8", "offset": "0x9a8"}, {"name": "CAU_ROTL_CASR", "offset": "0x9c0"}, {"name": "CAU_ROTL_CAA", "offset": "0x9c4"}, {"name": "CAU_ROTL_CA0", "offset": "0x9c8"}, {"name": "CAU_ROTL_CA1", "offset": "0x9cc"}, {"name": "CAU_ROTL_CA2", "offset": "0x9d0"}, {"name": "CAU_ROTL_CA3", "offset": "0x9d4"}, {"name": "CAU_ROTL_CA4", "offset": "0x9d8"}, {"name": "CAU_ROTL_CA5", "offset": "0x9dc"}, {"name": "CAU_ROTL_CA6", "offset": "0x9e0"}, {"name": "CAU_ROTL_CA7", "offset": "0x9e4"}, {"name": "CAU_ROTL_CA8", "offset": "0x9e8"}, {"name": "CAU_AESC_CASR", "offset": "0xb00"}, {"name": "CAU_AESC_CAA", "offset": "0xb04"}, {"name": "CAU_AESC_CA0", "offset": "0xb08"}, {"name": "CAU_AESC_CA1", "offset": "0xb0c"}, {"name": "CAU_AESC_CA2", "offset": "0xb10"}, {"name": "CAU_AESC_CA3", "offset": "0xb14"}, {"name": "CAU_AESC_CA4", "offset": "0xb18"}, {"name": "CAU_AESC_CA5", "offset": "0xb1c"}, {"name": "CAU_AESC_CA6", "offset": "0xb20"}, {"name": "CAU_AESC_CA7", "offset": "0xb24"}, {"name": "CAU_AESC_CA8", "offset": "0xb28"}, {"name": "CAU_AESIC_CASR", "offset": "0xb40"}, {"name": "CAU_AESIC_CAA", "offset": "0xb44"}, {"name": "CAU_AESIC_CA0", "offset": "0xb48"}, {"name": "CAU_AESIC_CA1", "offset": "0xb4c"}, {"name": "CAU_AESIC_CA2", "offset": "0xb50"}, {"name": "CAU_AESIC_CA3", "offset": "0xb54"}, {"name": "CAU_AESIC_CA4", "offset": "0xb58"}, {"name": "CAU_AESIC_CA5", "offset": "0xb5c"}, {"name": "CAU_AESIC_CA6", "offset": "0xb60"}, {"name": "CAU_AESIC_CA7", "offset": "0xb64"}, {"name": "CAU_AESIC_CA8", "offset": "0xb68"}]}], "vector_table": [{"name": "StackPointer_Value", "value": -1, "addr": "0x0", "comment": "Stack pointer initial value"}, {"name": "Reset", "value": -1, "addr": "0x4", "comment": "Priority: -3"}, {"name": "NMI", "value": -1, "addr": "0x8", "comment": "Priority: -2"}, {"name": "HardFault", "value": -1, "addr": "0xc", "comment": "Priority: -1"}, {"name": "SVCall", "value": -1, "addr": "0x2c", "comment": "Priority: 3"}, {"name": "PendSV", "value": -1, "addr": "0x38", "comment": "Priority: 5"}, {"name": "SysTick", "value": -1, "addr": "0x3c", "comment": "Priority: 6"}, {"name": "DMA0", "value": 0, "comment": "", "addr": "0x40"}, {"name": "DMA1", "value": 1, "comment": "", "addr": "0x44"}, {"name": "DMA2", "value": 2, "comment": "", "addr": "0x48"}, {"name": "DMA3", "value": 3, "comment": "", "addr": "0x4c"}, {"name": "DMA4", "value": 4, "comment": "", "addr": "0x50"}, {"name": "DMA5", "value": 5, "comment": "", "addr": "0x54"}, {"name": "DMA6", "value": 6, "comment": "", "addr": "0x58"}, {"name": "DMA7", "value": 7, "comment": "", "addr": "0x5c"}, {"name": "DMA8", "value": 8, "comment": "", "addr": "0x60"}, {"name": "DMA9", "value": 9, "comment": "", "addr": "0x64"}, {"name": "DMA10", "value": 10, "comment": "", "addr": "0x68"}, {"name": "DMA11", "value": 11, "comment": "", "addr": "0x6c"}, {"name": "DMA12", "value": 12, "comment": "", "addr": "0x70"}, {"name": "DMA13", "value": 13, "comment": "", "addr": "0x74"}, {"name": "DMA14", "value": 14, "comment": "", "addr": "0x78"}, {"name": "DMA15", "value": 15, "comment": "", "addr": "0x7c"}, {"name": "DMA_Error", "value": 16, "comment": "", "addr": "0x80"}, {"name": "MCM", "value": 17, "comment": "", "addr": "0x84"}, {"name": "FTFL", "value": 18, "comment": "", "addr": "0x88"}, {"name": "Read_Collision", "value": 19, "comment": "", "addr": "0x8c"}, {"name": "LVD_LVW", "value": 20, "comment": "", "addr": "0x90"}, {"name": "LLWU", "value": 21, "comment": "", "addr": "0x94"}, {"name": "WDOG_EWM", "value": 22, "comment": "", "addr": "0x98"}, {"name": "WDOG_EWM", "value": 22, "comment": "", "addr": "0x98"}, {"name": "RNG", "value": 23, "comment": "", "addr": "0x9c"}, {"name": "I2C0", "value": 24, "comment": "", "addr": "0xa0"}, {"name": "I2C1", "value": 25, "comment": "", "addr": "0xa4"}, {"name": "SPI0", "value": 26, "comment": "", "addr": "0xa8"}, {"name": "SPI1", "value": 27, "comment": "", "addr": "0xac"}, {"name": "SPI2", "value": 28, "comment": "", "addr": "0xb0"}, {"name": "I2S0_Tx", "value": 35, "comment": "", "addr": "0xcc"}, {"name": "I2S0_Rx", "value": 36, "comment": "", "addr": "0xd0"}, {"name": "UART0_LON", "value": 44, "comment": "", "addr": "0xf0"}, {"name": "UART0_RX_TX", "value": 45, "comment": "", "addr": "0xf4"}, {"name": "UART0_ERR", "value": 46, "comment": "", "addr": "0xf8"}, {"name": "UART1_RX_TX", "value": 47, "comment": "", "addr": "0xfc"}, {"name": "UART1_ERR", "value": 48, "comment": "", "addr": "0x100"}, {"name": "UART2_RX_TX", "value": 49, "comment": "", "addr": "0x104"}, {"name": "UART2_ERR", "value": 50, "comment": "", "addr": "0x108"}, {"name": "UART3_RX_TX", "value": 51, "comment": "", "addr": "0x10c"}, {"name": "UART3_ERR", "value": 52, "comment": "", "addr": "0x110"}, {"name": "UART4_RX_TX", "value": 53, "comment": "", "addr": "0x114"}, {"name": "UART4_ERR", "value": 54, "comment": "", "addr": "0x118"}, {"name": "UART5_RX_TX", "value": 55, "comment": "", "addr": "0x11c"}, {"name": "UART5_ERR", "value": 56, "comment": "", "addr": "0x120"}, {"name": "ADC0", "value": 57, "comment": "", "addr": "0x124"}, {"name": "ADC1", "value": 58, "comment": "", "addr": "0x128"}, {"name": "CMP0", "value": 59, "comment": "", "addr": "0x12c"}, {"name": "CMP1", "value": 60, "comment": "", "addr": "0x130"}, {"name": "CMP2", "value": 61, "comment": "", "addr": "0x134"}, {"name": "FTM0", "value": 62, "comment": "", "addr": "0x138"}, {"name": "FTM1", "value": 63, "comment": "", "addr": "0x13c"}, {"name": "FTM2", "value": 64, "comment": "", "addr": "0x140"}, {"name": "CMT", "value": 65, "comment": "", "addr": "0x144"}, {"name": "RTC", "value": 66, "comment": "", "addr": "0x148"}, {"name": "RTC_Seconds", "value": 67, "comment": "", "addr": "0x14c"}, {"name": "PIT0", "value": 68, "comment": "", "addr": "0x150"}, {"name": "PIT1", "value": 69, "comment": "", "addr": "0x154"}, {"name": "PIT2", "value": 70, "comment": "", "addr": "0x158"}, {"name": "PIT3", "value": 71, "comment": "", "addr": "0x15c"}, {"name": "PDB0", "value": 72, "comment": "", "addr": "0x160"}, {"name": "USB0", "value": 73, "comment": "", "addr": "0x164"}, {"name": "USBDCD", "value": 74, "comment": "", "addr": "0x168"}, {"name": "ENET_1588_Timer", "value": 75, "comment": "", "addr": "0x16c"}, {"name": "ENET_Transmit", "value": 76, "comment": "", "addr": "0x170"}, {"name": "ENET_Receive", "value": 77, "comment": "", "addr": "0x174"}, {"name": "ENET_Error", "value": 78, "comment": "", "addr": "0x178"}, {"name": "SDHC", "value": 80, "comment": "", "addr": "0x180"}, {"name": "DAC0", "value": 81, "comment": "", "addr": "0x184"}, {"name": "DAC1", "value": 82, "comment": "", "addr": "0x188"}, {"name": "TSI0", "value": 83, "comment": "", "addr": "0x18c"}, {"name": "MCG", "value": 84, "comment": "", "addr": "0x190"}, {"name": "LPTMR0", "value": 85, "comment": "", "addr": "0x194"}, {"name": "PORTA", "value": 87, "comment": "", "addr": "0x19c"}, {"name": "PORTA", "value": 87, "comment": "", "addr": "0x19c"}, {"name": "PORTB", "value": 88, "comment": "", "addr": "0x1a0"}, {"name": "PORTB", "value": 88, "comment": "", "addr": "0x1a0"}, {"name": "PORTC", "value": 89, "comment": "", "addr": "0x1a4"}, {"name": "PORTC", "value": 89, "comment": "", "addr": "0x1a4"}, {"name": "PORTD", "value": 90, "comment": "", "addr": "0x1a8"}, {"name": "PORTD", "value": 90, "comment": "", "addr": "0x1a8"}, {"name": "PORTE", "value": 91, "comment": "", "addr": "0x1ac"}, {"name": "PORTE", "value": 91, "comment": "", "addr": "0x1ac"}]}